Workbook

Sheet Returns
B2: Levered and unlevered returns — single loan tranche, quarterly
B3: Blue cells are editable inputs (example values shown). Every line a chat render shows is its own cell. Interest = beginning balance x rate / 4.
B5: Investment terms | H5: Leverage
B6: Face amount ($MM) | C6: 100 | H6: Leverage (X of equity) — 1.0x = dollar-for-dollar | I6: 1
B7: Loan spread over SOFR (bps) | C7: 600 | H7: Implied advance rate | I7: =I6/(1+I6)
B8: Issue price / OID (100 = no discount; 98 = 2% discount) | C8: 98 | D8: =1-C8/100 | E8: OID discount | H8: Leverage spread over SOFR (bps) | I8: 300
B9: Hold period (quarters, 1 to 20) | C9: 12 | H9: Financing line at close ($MM) | I9: =C6*(1-D8)*I7
B10: PIK period (quarters; 0 = none) | C10: 0 | H10: Financing line = advance rate x funded amount (face less OID). It is paid down pro rata with the loan's scheduled principal repayments and the remainder is repaid at exit. PIK interest does not change it.
B11: Amortization (% of original face per year) | C11: 0.01 | H11: No amortization is paid during a PIK period. PIK interest is added to the loan balance at the loan's all-in rate.
B12: Exit price (% of par; 100 = par) | C12: 100
B13: Funding date | C13: 46295
B14: Curve shift (quarters; nearest quarter start to the funding date) | C14: =IF(C13<Curve!$D$6,0,MAX(0,ROUND(((YEAR(C13)-YEAR(Curve!$D$6))*12+MONTH(C13)-MONTH(Curve!$D$6))/3,0)))
B15: Curve status | C15: =IF(C13<Curve!$D$6,"Funding date is before the curve date; curve applied from quarter 1 regardless",IF(C14+C9>20,"Curve runs out after quarter "&(20-C14)&"; last rate held flat","Curve covers the full hold"))
B18: Quarterly engine
B19: Quarter | C19: 0 | D19: 1 | E19: 2 | F19: 3 | G19: 4 | H19: 5 | I19: 6 | J19: 7 | K19: 8 | L19: 9 | M19: 10 | N19: 11 | O19: 12 | P19: 13 | Q19: 14 | R19: 15 | S19: 16 | T19: 17 | U19: 18 | V19: 19 | W19: 20
B20: Active (1 = inside hold) | D20: =IF(AND(D$19>=1,D$19<=$C$9),1,0) | E20: =IF(AND(E$19>=1,E$19<=$C$9),1,0) | F20: =IF(AND(F$19>=1,F$19<=$C$9),1,0) | G20: =IF(AND(G$19>=1,G$19<=$C$9),1,0) | H20: =IF(AND(H$19>=1,H$19<=$C$9),1,0) | I20: =IF(AND(I$19>=1,I$19<=$C$9),1,0) | J20: =IF(AND(J$19>=1,J$19<=$C$9),1,0) | K20: =IF(AND(K$19>=1,K$19<=$C$9),1,0) | ... W20: =IF(AND(W$19>=1,W$19<=$C$9),1,0)
B21: Exit quarter (1 = exit) | D21: =IF(D$19=$C$9,1,0) | E21: =IF(E$19=$C$9,1,0) | F21: =IF(F$19=$C$9,1,0) | G21: =IF(G$19=$C$9,1,0) | H21: =IF(H$19=$C$9,1,0) | I21: =IF(I$19=$C$9,1,0) | J21: =IF(J$19=$C$9,1,0) | K21: =IF(K$19=$C$9,1,0) | ... W21: =IF(W$19=$C$9,1,0)
B22: SOFR forward (Curve tab, shifted to funding date) | D22: =IF(D20=1,INDEX(Curve!$C$6:$C$25,MIN(20,D$19+$C$14)),0) | E22: =IF(E20=1,INDEX(Curve!$C$6:$C$25,MIN(20,E$19+$C$14)),0) | F22: =IF(F20=1,INDEX(Curve!$C$6:$C$25,MIN(20,F$19+$C$14)),0) | G22: =IF(G20=1,INDEX(Curve!$C$6:$C$25,MIN(20,G$19+$C$14)),0) | H22: =IF(H20=1,INDEX(Curve!$C$6:$C$25,MIN(20,H$19+$C$14)),0) | I22: =IF(I20=1,INDEX(Curve!$C$6:$C$25,MIN(20,I$19+$C$14)),0) | J22: =IF(J20=1,INDEX(Curve!$C$6:$C$25,MIN(20,J$19+$C$14)),0) | K22: =IF(K20=1,INDEX(Curve!$C$6:$C$25,MIN(20,K$19+$C$14)),0) | ... W22: =IF(W20=1,INDEX(Curve!$C$6:$C$25,MIN(20,W$19+$C$14)),0)
B23: Loan all-in rate | D23: =IF(D20=1,D22+$C$7/10000,0) | E23: =IF(E20=1,E22+$C$7/10000,0) | F23: =IF(F20=1,F22+$C$7/10000,0) | G23: =IF(G20=1,G22+$C$7/10000,0) | H23: =IF(H20=1,H22+$C$7/10000,0) | I23: =IF(I20=1,I22+$C$7/10000,0) | J23: =IF(J20=1,J22+$C$7/10000,0) | K23: =IF(K20=1,K22+$C$7/10000,0) | ... W23: =IF(W20=1,W22+$C$7/10000,0)
B24: PIK flag (1 = PIK quarter) | D24: =IF(AND(D20=1,D$19<=$C$10),1,0) | E24: =IF(AND(E20=1,E$19<=$C$10),1,0) | F24: =IF(AND(F20=1,F$19<=$C$10),1,0) | G24: =IF(AND(G20=1,G$19<=$C$10),1,0) | H24: =IF(AND(H20=1,H$19<=$C$10),1,0) | I24: =IF(AND(I20=1,I$19<=$C$10),1,0) | J24: =IF(AND(J20=1,J$19<=$C$10),1,0) | K24: =IF(AND(K20=1,K$19<=$C$10),1,0) | ... W24: =IF(AND(W20=1,W$19<=$C$10),1,0)
B25: Loan beginning balance | D25: =C29 | E25: =D29 | F25: =E29 | G25: =F29 | H25: =G29 | I25: =H29 | J25: =I29 | K25: =J29 | ... W25: =V29
B26: Interest accrued | D26: =D20*D25*D23/4 | E26: =E20*E25*E23/4 | F26: =F20*F25*F23/4 | G26: =G20*G25*G23/4 | H26: =H20*H25*H23/4 | I26: =I20*I25*I23/4 | J26: =J20*J25*J23/4 | K26: =K20*K25*K23/4 | ... W26: =W20*W25*W23/4
B27: PIK capitalized | D27: =D24*D26 | E27: =E24*E26 | F27: =F24*F26 | G27: =G24*G26 | H27: =H24*H26 | I27: =I24*I26 | J27: =J24*J26 | K27: =K24*K26 | ... W27: =W24*W26
B28: Scheduled amortization | D28: =IF(AND(D20=1,D24=0),MIN(D25,$C$6*$C$11/4),0) | E28: =IF(AND(E20=1,E24=0),MIN(E25,$C$6*$C$11/4),0) | F28: =IF(AND(F20=1,F24=0),MIN(F25,$C$6*$C$11/4),0) | G28: =IF(AND(G20=1,G24=0),MIN(G25,$C$6*$C$11/4),0) | H28: =IF(AND(H20=1,H24=0),MIN(H25,$C$6*$C$11/4),0) | I28: =IF(AND(I20=1,I24=0),MIN(I25,$C$6*$C$11/4),0) | J28: =IF(AND(J20=1,J24=0),MIN(J25,$C$6*$C$11/4),0) | K28: =IF(AND(K20=1,K24=0),MIN(K25,$C$6*$C$11/4),0) | ... W28: =IF(AND(W20=1,W24=0),MIN(W25,$C$6*$C$11/4),0)
B29: Loan ending balance before exit payoff | C29: =$C$6 | D29: =IF(D20=1,D25+D27-D28,0) | E29: =IF(E20=1,E25+E27-E28,0) | F29: =IF(F20=1,F25+F27-F28,0) | G29: =IF(G20=1,G25+G27-G28,0) | H29: =IF(H20=1,H25+H27-H28,0) | I29: =IF(I20=1,I25+I27-I28,0) | J29: =IF(J20=1,J25+J27-J28,0) | K29: =IF(K20=1,K25+K27-K28,0) | ... W29: =IF(W20=1,W25+W27-W28,0)
B30: Financing line beginning balance | D30: =C32 | E30: =D32 | F30: =E32 | G30: =F32 | H30: =G32 | I30: =H32 | J30: =I32 | K30: =J32 | ... W30: =V32
B31: Financing paydown (pro rata with amortization) | D31: =IF(D20=1,$I$9*D28/$C$6,0) | E31: =IF(E20=1,$I$9*E28/$C$6,0) | F31: =IF(F20=1,$I$9*F28/$C$6,0) | G31: =IF(G20=1,$I$9*G28/$C$6,0) | H31: =IF(H20=1,$I$9*H28/$C$6,0) | I31: =IF(I20=1,$I$9*I28/$C$6,0) | J31: =IF(J20=1,$I$9*J28/$C$6,0) | K31: =IF(K20=1,$I$9*K28/$C$6,0) | ... W31: =IF(W20=1,$I$9*W28/$C$6,0)
B32: Financing line ending balance before exit payoff | C32: =$I$9 | D32: =IF(D20=1,D30-D31,0) | E32: =IF(E20=1,E30-E31,0) | F32: =IF(F20=1,F30-F31,0) | G32: =IF(G20=1,G30-G31,0) | H32: =IF(H20=1,H30-H31,0) | I32: =IF(I20=1,I30-I31,0) | J32: =IF(J20=1,J30-J31,0) | K32: =IF(K20=1,K30-K31,0) | ... W32: =IF(W20=1,W30-W31,0)
B34: Cash flows — every row is a real cell
B35: Quarter | C35: 0 | D35: 1 | E35: 2 | F35: 3 | G35: 4 | H35: 5 | I35: 6 | J35: 7 | K35: 8 | L35: 9 | M35: 10 | N35: 11 | O35: 12 | P35: 13 | Q35: 14 | R35: 15 | S35: 16 | T35: 17 | U35: 18 | V35: 19 | W35: 20
B36: Initial Funding | C36: =-$C$6*(1-$D$8) | D36: 0 | E36: 0 | F36: 0 | G36: 0 | H36: 0 | I36: 0 | J36: 0 | K36: 0 | L36: 0 | M36: 0 | N36: 0 | O36: 0 | P36: 0 | Q36: 0 | R36: 0 | S36: 0 | T36: 0 | U36: 0 | V36: 0 | W36: 0
B37: (+) Sub line draw | C37: =$I$9 | D37: 0 | E37: 0 | F37: 0 | G37: 0 | H37: 0 | I37: 0 | J37: 0 | K37: 0 | L37: 0 | M37: 0 | N37: 0 | O37: 0 | P37: 0 | Q37: 0 | R37: 0 | S37: 0 | T37: 0 | U37: 0 | V37: 0 | W37: 0
B38: (+) Cash Interest | C38: 0 | D38: =D26-D27 | E38: =E26-E27 | F38: =F26-F27 | G38: =G26-G27 | H38: =H26-H27 | I38: =I26-I27 | J38: =J26-J27 | K38: =K26-K27 | ... W38: =W26-W27
B39: (+) Mandatory Prepayments | C39: 0 | D39: =D28 | E39: =E28 | F39: =F28 | G39: =G28 | H39: =H28 | I39: =I28 | J39: =J28 | K39: =K28 | ... W39: =W28
B40: (-) Interest on Sub line | C40: 0 | D40: =-D20*D30*(D22+$I$8/10000)/4 | E40: =-E20*E30*(E22+$I$8/10000)/4 | F40: =-F20*F30*(F22+$I$8/10000)/4 | G40: =-G20*G30*(G22+$I$8/10000)/4 | H40: =-H20*H30*(H22+$I$8/10000)/4 | I40: =-I20*I30*(I22+$I$8/10000)/4 | J40: =-J20*J30*(J22+$I$8/10000)/4 | K40: =-K20*K30*(K22+$I$8/10000)/4 | ... W40: =-W20*W30*(W22+$I$8/10000)/4
B41: (-) Sub line paydown (pro rata) | C41: 0 | D41: =-D31 | E41: =-E31 | F41: =-F31 | G41: =-G31 | H41: =-H31 | I41: =-I31 | J41: =-J31 | K41: =-K31 | ... W41: =-W31
B42: (+) Final Payoffs | C42: 0 | D42: =D21*D29*$C$12/100 | E42: =E21*E29*$C$12/100 | F42: =F21*F29*$C$12/100 | G42: =G21*G29*$C$12/100 | H42: =H21*H29*$C$12/100 | I42: =I21*I29*$C$12/100 | J42: =J21*J29*$C$12/100 | K42: =K21*K29*$C$12/100 | ... W42: =W21*W29*$C$12/100
B43: (-) Sub line Payoff | C43: 0 | D43: =-D21*D32 | E43: =-E21*E32 | F43: =-F21*F32 | G43: =-G21*G32 | H43: =-H21*H32 | I43: =-I21*I32 | J43: =-J21*J32 | K43: =-K21*K32 | ... W43: =-W21*W32
B44: Total Cash Flows (Levered) | C44: =SUM(C36:C43) | D44: =SUM(D36:D43) | E44: =SUM(E36:E43) | F44: =SUM(F36:F43) | G44: =SUM(G36:G43) | H44: =SUM(H36:H43) | I44: =SUM(I36:I43) | J44: =SUM(J36:J43) | ... W44: =SUM(W36:W43)
B45: Total Cash Flows (Unlevered) | C45: =C36+C38+C39+C42 | D45: =D36+D38+D39+D42 | E45: =E36+E38+E39+E42 | F45: =F36+F38+F39+F42 | G45: =G36+G38+G39+G42 | H45: =H36+H38+H39+H42 | I45: =I36+I38+I39+I42 | J45: =J36+J38+J39+J42 | ... W45: =W36+W38+W39+W42
C47: Unlevered | D47: Levered
B48: Quarterly IRR | C48: =IRR(C45:W45,0.02) | D48: =IFERROR(IRR(C44:W44,0.02),"Undefined")
B49: IRR (annualized, effective) | C49: =(1+C48)^4-1 | D49: =IFERROR((1+D48)^4-1,"Undefined")
B50: IRR (nominal: quarterly IRR x 4) | C50: =C48*4 | D50: =IFERROR(D48*4,"Undefined")
B51: MOIC | C51: =SUMIF(C45:W45,">0")/-SUMIF(C45:W45,"<0") | D51: =SUMIF(C44:W44,">0")/-SUMIF(C44:W44,"<0")
B52: MOIC = total cash received / total cash paid out. Headline IRR is effective (compounded); nominal is shown for comparison with annual-pay conventions.
B54: Annual roll-up (sums of the quarterly rows above; Year 1 = quarters 1 to 4, and so on)
B55: Year | C55: 0 | D55: 1 | E55: 2 | F55: 3 | G55: 4 | H55: 5
B56: Initial Funding | C56: =C36 | D56: =SUMIFS($D36:$W36,$D$35:$W$35,">="&1,$D$35:$W$35,"<="&4) | E56: =SUMIFS($D36:$W36,$D$35:$W$35,">="&5,$D$35:$W$35,"<="&8) | F56: =SUMIFS($D36:$W36,$D$35:$W$35,">="&9,$D$35:$W$35,"<="&12) | G56: =SUMIFS($D36:$W36,$D$35:$W$35,">="&13,$D$35:$W$35,"<="&16) | H56: =SUMIFS($D36:$W36,$D$35:$W$35,">="&17,$D$35:$W$35,"<="&20)
B57: (+) Sub line draw | C57: =C37 | D57: =SUMIFS($D37:$W37,$D$35:$W$35,">="&1,$D$35:$W$35,"<="&4) | E57: =SUMIFS($D37:$W37,$D$35:$W$35,">="&5,$D$35:$W$35,"<="&8) | F57: =SUMIFS($D37:$W37,$D$35:$W$35,">="&9,$D$35:$W$35,"<="&12) | G57: =SUMIFS($D37:$W37,$D$35:$W$35,">="&13,$D$35:$W$35,"<="&16) | H57: =SUMIFS($D37:$W37,$D$35:$W$35,">="&17,$D$35:$W$35,"<="&20)
B58: (+) Cash Interest | C58: =C38 | D58: =SUMIFS($D38:$W38,$D$35:$W$35,">="&1,$D$35:$W$35,"<="&4) | E58: =SUMIFS($D38:$W38,$D$35:$W$35,">="&5,$D$35:$W$35,"<="&8) | F58: =SUMIFS($D38:$W38,$D$35:$W$35,">="&9,$D$35:$W$35,"<="&12) | G58: =SUMIFS($D38:$W38,$D$35:$W$35,">="&13,$D$35:$W$35,"<="&16) | H58: =SUMIFS($D38:$W38,$D$35:$W$35,">="&17,$D$35:$W$35,"<="&20)
B59: (+) Mandatory Prepayments | C59: =C39 | D59: =SUMIFS($D39:$W39,$D$35:$W$35,">="&1,$D$35:$W$35,"<="&4) | E59: =SUMIFS($D39:$W39,$D$35:$W$35,">="&5,$D$35:$W$35,"<="&8) | F59: =SUMIFS($D39:$W39,$D$35:$W$35,">="&9,$D$35:$W$35,"<="&12) | G59: =SUMIFS($D39:$W39,$D$35:$W$35,">="&13,$D$35:$W$35,"<="&16) | H59: =SUMIFS($D39:$W39,$D$35:$W$35,">="&17,$D$35:$W$35,"<="&20)
B60: (-) Interest on Sub line | C60: =C40 | D60: =SUMIFS($D40:$W40,$D$35:$W$35,">="&1,$D$35:$W$35,"<="&4) | E60: =SUMIFS($D40:$W40,$D$35:$W$35,">="&5,$D$35:$W$35,"<="&8) | F60: =SUMIFS($D40:$W40,$D$35:$W$35,">="&9,$D$35:$W$35,"<="&12) | G60: =SUMIFS($D40:$W40,$D$35:$W$35,">="&13,$D$35:$W$35,"<="&16) | H60: =SUMIFS($D40:$W40,$D$35:$W$35,">="&17,$D$35:$W$35,"<="&20)
B61: (-) Sub line paydown (pro rata) | C61: =C41 | D61: =SUMIFS($D41:$W41,$D$35:$W$35,">="&1,$D$35:$W$35,"<="&4) | E61: =SUMIFS($D41:$W41,$D$35:$W$35,">="&5,$D$35:$W$35,"<="&8) | F61: =SUMIFS($D41:$W41,$D$35:$W$35,">="&9,$D$35:$W$35,"<="&12) | G61: =SUMIFS($D41:$W41,$D$35:$W$35,">="&13,$D$35:$W$35,"<="&16) | H61: =SUMIFS($D41:$W41,$D$35:$W$35,">="&17,$D$35:$W$35,"<="&20)
B62: (+) Final Payoffs | C62: =C42 | D62: =SUMIFS($D42:$W42,$D$35:$W$35,">="&1,$D$35:$W$35,"<="&4) | E62: =SUMIFS($D42:$W42,$D$35:$W$35,">="&5,$D$35:$W$35,"<="&8) | F62: =SUMIFS($D42:$W42,$D$35:$W$35,">="&9,$D$35:$W$35,"<="&12) | G62: =SUMIFS($D42:$W42,$D$35:$W$35,">="&13,$D$35:$W$35,"<="&16) | H62: =SUMIFS($D42:$W42,$D$35:$W$35,">="&17,$D$35:$W$35,"<="&20)
B63: (-) Sub line Payoff | C63: =C43 | D63: =SUMIFS($D43:$W43,$D$35:$W$35,">="&1,$D$35:$W$35,"<="&4) | E63: =SUMIFS($D43:$W43,$D$35:$W$35,">="&5,$D$35:$W$35,"<="&8) | F63: =SUMIFS($D43:$W43,$D$35:$W$35,">="&9,$D$35:$W$35,"<="&12) | G63: =SUMIFS($D43:$W43,$D$35:$W$35,">="&13,$D$35:$W$35,"<="&16) | H63: =SUMIFS($D43:$W43,$D$35:$W$35,">="&17,$D$35:$W$35,"<="&20)
B64: Total Cash Flows (Levered) | C64: =C44 | D64: =SUMIFS($D44:$W44,$D$35:$W$35,">="&1,$D$35:$W$35,"<="&4) | E64: =SUMIFS($D44:$W44,$D$35:$W$35,">="&5,$D$35:$W$35,"<="&8) | F64: =SUMIFS($D44:$W44,$D$35:$W$35,">="&9,$D$35:$W$35,"<="&12) | G64: =SUMIFS($D44:$W44,$D$35:$W$35,">="&13,$D$35:$W$35,"<="&16) | H64: =SUMIFS($D44:$W44,$D$35:$W$35,">="&17,$D$35:$W$35,"<="&20)
B65: Total Cash Flows (Unlevered) | C65: =C45 | D65: =SUMIFS($D45:$W45,$D$35:$W$35,">="&1,$D$35:$W$35,"<="&4) | E65: =SUMIFS($D45:$W45,$D$35:$W$35,">="&5,$D$35:$W$35,"<="&8) | F65: =SUMIFS($D45:$W45,$D$35:$W$35,">="&9,$D$35:$W$35,"<="&12) | G65: =SUMIFS($D45:$W45,$D$35:$W$35,">="&13,$D$35:$W$35,"<="&16) | H65: =SUMIFS($D45:$W45,$D$35:$W$35,">="&17,$D$35:$W$35,"<="&20)
B67: Sensitivity Table — Levered IRR (annualized): spread vs. leverage multiple (hold, PIK, amortization, exit price as set above)
D68: Leverage (x)
B69: Coupon (first quarter) | C69: Spread (bps) | D69: 0.75 | E69: 1 | F69: 1.25
B70: =INDEX(Curve!$C$6:$C$25,MIN(20,1+$C$14))+C70/10000 | C70: =Sens!C7 | D70: =IFERROR((1+IRR(Sens!C10:W10,0.02))^4-1,"Undefined") | E70: =IFERROR((1+IRR(Sens!C15:W15,0.02))^4-1,"Undefined") | F70: =IFERROR((1+IRR(Sens!C20:W20,0.02))^4-1,"Undefined")
B71: =INDEX(Curve!$C$6:$C$25,MIN(20,1+$C$14))+C71/10000 | C71: =Sens!C22 | D71: =IFERROR((1+IRR(Sens!C25:W25,0.02))^4-1,"Undefined") | E71: =IFERROR((1+IRR(Sens!C30:W30,0.02))^4-1,"Undefined") | F71: =IFERROR((1+IRR(Sens!C35:W35,0.02))^4-1,"Undefined")
B72: =INDEX(Curve!$C$6:$C$25,MIN(20,1+$C$14))+C72/10000 | C72: =Sens!C37 | D72: =IFERROR((1+IRR(Sens!C40:W40,0.02))^4-1,"Undefined") | E72: =IFERROR((1+IRR(Sens!C45:W45,0.02))^4-1,"Undefined") | F72: =IFERROR((1+IRR(Sens!C50:W50,0.02))^4-1,"Undefined")
B73: =INDEX(Curve!$C$6:$C$25,MIN(20,1+$C$14))+C73/10000 | C73: =Sens!C52 | D73: =IFERROR((1+IRR(Sens!C55:W55,0.02))^4-1,"Undefined") | E73: =IFERROR((1+IRR(Sens!C60:W60,0.02))^4-1,"Undefined") | F73: =IFERROR((1+IRR(Sens!C65:W65,0.02))^4-1,"Undefined")
B74: =INDEX(Curve!$C$6:$C$25,MIN(20,1+$C$14))+C74/10000 | C74: =Sens!C67 | D74: =IFERROR((1+IRR(Sens!C70:W70,0.02))^4-1,"Undefined") | E74: =IFERROR((1+IRR(Sens!C75:W75,0.02))^4-1,"Undefined") | F74: =IFERROR((1+IRR(Sens!C80:W80,0.02))^4-1,"Undefined")
B76: Reconciliation check (1.0x column at the real spread vs. main levered IRR; applies only when the leverage input is 1.00x):
B77: =IF($I$6=1,IF(ABS(E72-D49)<0.0000001,"OK — reconciles","MISMATCH"),"n/a (leverage input is not 1.00x)")

Sheet Curve
B2: Quarterly SOFR forward assumption (used by the Returns tab)
B3: Overnight-SOFR-derived forward proxy, NOT CME Term SOFR. Quarter 1 starts on the date in D6 (curve as-of date). The Returns tab shifts the curve to the funding date. An uploaded curve overwrites C6:C25 and D6.
B5: Quarter | C5: SOFR forward used | D5: Quarter starts | E5: Basis
B6: 1 | C6: 0.0408 | D6: 46295 | E6: Anchor: 3M swap rate (Oct 15, 2026)
B7: 2 | C7: 0.0428 | D7: =EOMONTH(D6,3) | E7: Anchor: 3M forward, year-end (Oct 16, 2026)
B8: 3 | C8: 0.04365 | D8: =EOMONTH(D7,3) | E8: Straight-line between anchors
B9: 4 | C9: 0.0445 | D9: =EOMONTH(D8,3) | E9: Straight-line between anchors
B10: 5 | C10: 0.04535 | D10: =EOMONTH(D9,3) | E10: Straight-line between anchors
B11: 6 | C11: 0.0462 | D11: =EOMONTH(D10,3) | E11: Anchor: 3M forward, year-end (Oct 16, 2026)
B12: 7 | C12: 0.0464 | D12: =EOMONTH(D11,3) | E12: Straight-line between anchors
B13: 8 | C13: 0.0466 | D13: =EOMONTH(D12,3) | E13: Straight-line between anchors
B14: 9 | C14: 0.0468 | D14: =EOMONTH(D13,3) | E14: Straight-line between anchors
B15: 10 | C15: 0.047 | D15: =EOMONTH(D14,3) | E15: Anchor: 3M forward, year-end (Oct 16, 2026)
B16: 11 | C16: 0.046575 | D16: =EOMONTH(D15,3) | E16: Straight-line between anchors
B17: 12 | C17: 0.04615 | D17: =EOMONTH(D16,3) | E17: Straight-line between anchors
B18: 13 | C18: 0.045725 | D18: =EOMONTH(D17,3) | E18: Straight-line between anchors
... B25: 20 | C25: 0.0453 | D25: =EOMONTH(D24,3) | E25: Held flat after last published point
B28: Anchor sources
B29: Quarter 1: USD SOFR swap rate, 3 Month, Sept 24, 2026 (bluegamma.io/usd-swap-rates). Spot overnight SOFR was 3.88% (Sept 29, 2026).
B30: Quarter starting Dec 31, 2026 / 2027 / 2028 / 2029: SOFR forward, 4.38% / 4.82% / 4.91% / 4.70% (bluegamma.io/sofr-forward-curve, updated Sept 29, 2026).
B31: Quarters between anchors are straight-line interpolated. After Dec 2029 the rate is held flat at 4.70% (an assumption; the free source does not publish beyond 2029).
B32: Derived from overnight SOFR swaps; a proxy for forward SOFR, not CME Term SOFR. Replace with a Term SOFR curve for decision-grade analysis.

Sheet Sens
B2: Sensitivity working area (levered): 5 spread offsets x 3 leverage multiples, each a full independent cash flow
B3: Same formulas as the Returns tab. Hold, PIK, amortization, exit price and curve shift come from the Returns tab inputs.
B5: Quarter | C5: 0 | D5: 1 | E5: 2 | F5: 3 | G5: 4 | H5: 5 | I5: 6 | J5: 7 | K5: 8 | L5: 9 | M5: 10 | N5: 11 | O5: 12 | P5: 13 | Q5: 14 | R5: 15 | S5: 16 | T5: 17 | U5: 18 | V5: 19 | W5: 20
B7: Spread offset -100 bps, leverage 0.75x — parameters (spread, leverage, advance rate, financing at close) | C7: =Returns!$C$7+(-100) | D7: 0.75 | E7: =D7/(1+D7) | F7: =Returns!$C$6*(1-Returns!$D$8)*E7
B8: Loan ending balance (before exit payoff) | C8: =Returns!$C$6 | D8: =IF(Returns!D20=1,C8+Returns!D24*C8*(Returns!D22+$C7/10000)/4-IF(AND(Returns!D20=1,Returns!D24=0),MIN(C8,Returns!$C$6*Returns!$C$11/4),0),0) | E8: =IF(Returns!E20=1,D8+Returns!E24*D8*(Returns!E22+$C7/10000)/4-IF(AND(Returns!E20=1,Returns!E24=0),MIN(D8,Returns!$C$6*Returns!$C$11/4),0),0) | F8: =IF(Returns!F20=1,E8+Returns!F24*E8*(Returns!F22+$C7/10000)/4-IF(AND(Returns!F20=1,Returns!F24=0),MIN(E8,Returns!$C$6*Returns!$C$11/4),0),0) | G8: =IF(Returns!G20=1,F8+Returns!G24*F8*(Returns!G22+$C7/10000)/4-IF(AND(Returns!G20=1,Returns!G24=0),MIN(F8,Returns!$C$6*Returns!$C$11/4),0),0) | H8: =IF(Returns!H20=1,G8+Returns!H24*G8*(Returns!H22+$C7/10000)/4-IF(AND(Returns!H20=1,Returns!H24=0),MIN(G8,Returns!$C$6*Returns!$C$11/4),0),0) | I8: =IF(Returns!I20=1,H8+Returns!I24*H8*(Returns!I22+$C7/10000)/4-IF(AND(Returns!I20=1,Returns!I24=0),MIN(H8,Returns!$C$6*Returns!$C$11/4),0),0) | J8: =IF(Returns!J20=1,I8+Returns!J24*I8*(Returns!J22+$C7/10000)/4-IF(AND(Returns!J20=1,Returns!J24=0),MIN(I8,Returns!$C$6*Returns!$C$11/4),0),0) | K8: =IF(Returns!K20=1,J8+Returns!K24*J8*(Returns!K22+$C7/10000)/4-IF(AND(Returns!K20=1,Returns!K24=0),MIN(J8,Returns!$C$6*Returns!$C$11/4),0),0) | ... W8: =IF(Returns!W20=1,V8+Returns!W24*V8*(Returns!W22+$C7/10000)/4-IF(AND(Returns!W20=1,Returns!W24=0),MIN(V8,Returns!$C$6*Returns!$C$11/4),0),0)
B9: Financing line ending balance (before exit payoff) | C9: =$F7 | D9: =IF(Returns!D20=1,C9-$F7*IF(AND(Returns!D20=1,Returns!D24=0),MIN(C8,Returns!$C$6*Returns!$C$11/4),0)/Returns!$C$6,0) | E9: =IF(Returns!E20=1,D9-$F7*IF(AND(Returns!E20=1,Returns!E24=0),MIN(D8,Returns!$C$6*Returns!$C$11/4),0)/Returns!$C$6,0) | F9: =IF(Returns!F20=1,E9-$F7*IF(AND(Returns!F20=1,Returns!F24=0),MIN(E8,Returns!$C$6*Returns!$C$11/4),0)/Returns!$C$6,0) | G9: =IF(Returns!G20=1,F9-$F7*IF(AND(Returns!G20=1,Returns!G24=0),MIN(F8,Returns!$C$6*Returns!$C$11/4),0)/Returns!$C$6,0) | H9: =IF(Returns!H20=1,G9-$F7*IF(AND(Returns!H20=1,Returns!H24=0),MIN(G8,Returns!$C$6*Returns!$C$11/4),0)/Returns!$C$6,0) | I9: =IF(Returns!I20=1,H9-$F7*IF(AND(Returns!I20=1,Returns!I24=0),MIN(H8,Returns!$C$6*Returns!$C$11/4),0)/Returns!$C$6,0) | J9: =IF(Returns!J20=1,I9-$F7*IF(AND(Returns!J20=1,Returns!J24=0),MIN(I8,Returns!$C$6*Returns!$C$11/4),0)/Returns!$C$6,0) | K9: =IF(Returns!K20=1,J9-$F7*IF(AND(Returns!K20=1,Returns!K24=0),MIN(J8,Returns!$C$6*Returns!$C$11/4),0)/Returns!$C$6,0) | ... W9: =IF(Returns!W20=1,V9-$F7*IF(AND(Returns!W20=1,Returns!W24=0),MIN(V8,Returns!$C$6*Returns!$C$11/4),0)/Returns!$C$6,0)
B10: Levered net cash flow | C10: =-Returns!$C$6*(1-Returns!$D$8)+$F7 | D10: =Returns!D20*(1-Returns!D24)*C8*(Returns!D22+$C7/10000)/4+IF(AND(Returns!D20=1,Returns!D24=0),MIN(C8,Returns!$C$6*Returns!$C$11/4),0)+Returns!D21*D8*Returns!$C$12/100-Returns!D20*C9*(Returns!D22+Returns!$I$8/10000)/4-$F7*IF(AND(Returns!D20=1,Returns!D24=0),MIN(C8,Returns!$C$6*Returns!$C$11/4),0)/Returns!$C$6-Returns!D21*D9 | E10: =Returns!E20*(1-Returns!E24)*D8*(Returns!E22+$C7/10000)/4+IF(AND(Returns!E20=1,Returns!E24=0),MIN(D8,Returns!$C$6*Returns!$C$11/4),0)+Returns!E21*E8*Returns!$C$12/100-Returns!E20*D9*(Returns!E22+Returns!$I$8/10000)/4-$F7*IF(AND(Returns!E20=1,Returns!E24=0),MIN(D8,Returns!$C$6*Returns!$C$11/4),0)/Returns!$C$6-Returns!E21*E9 | F10: =Returns!F20*(1-Returns!F24)*E8*(Returns!F22+$C7/10000)/4+IF(AND(Returns!F20=1,Returns!F24=0),MIN(E8,Returns!$C$6*Returns!$C$11/4),0)+Returns!F21*F8*Returns!$C$12/100-Returns!F20*E9*(Returns!F22+Returns!$I$8/10000)/4-$F7*IF(AND(Returns!F20=1,Returns!F24=0),MIN(E8,Returns!$C$6*Returns!$C$11/4),0)/Returns!$C$6-Returns!F21*F9 | G10: =Returns!G20*(1-Returns!G24)*F8*(Returns!G22+$C7/10000)/4+IF(AND(Returns!G20=1,Returns!G24=0),MIN(F8,Returns!$C$6*Returns!$C$11/4),0)+Returns!G21*G8*Returns!$C$12/100-Returns!G20*F9*(Returns!G22+Returns!$I$8/10000)/4-$F7*IF(AND(Returns!G20=1,Returns!G24=0),MIN(F8,Returns!$C$6*Returns!$C$11/4),0)/Returns!$C$6-Returns!G21*G9 | H10: =Returns!H20*(1-Returns!H24)*G8*(Returns!H22+$C7/10000)/4+IF(AND(Returns!H20=1,Returns!H24=0),MIN(G8,Returns!$C$6*Returns!$C$11/4),0)+Returns!H21*H8*Returns!$C$12/100-Returns!H20*G9*(Returns!H22+Returns!$I$8/10000)/4-$F7*IF(AND(Returns!H20=1,Returns!H24=0),MIN(G8,Returns!$C$6*Returns!$C$11/4),0)/Returns!$C$6-Returns!H21*H9 | I10: =Returns!I20*(1-Returns!I24)*H8*(Returns!I22+$C7/10000)/4+IF(AND(Returns!I20=1,Returns!I24=0),MIN(H8,Returns!$C$6*Returns!$C$11/4),0)+Returns!I21*I8*Returns!$C$12/100-Returns!I20*H9*(Returns!I22+Returns!$I$8/10000)/4-$F7*IF(AND(Returns!I20=1,Returns!I24=0),MIN(H8,Returns!$C$6*Returns!$C$11/4),0)/Returns!$C$6-Returns!I21*I9 | J10: =Returns!J20*(1-Returns!J24)*I8*(Returns!J22+$C7/10000)/4+IF(AND(Returns!J20=1,Returns!J24=0),MIN(I8,Returns!$C$6*Returns!$C$11/4),0)+Returns!J21*J8*Returns!$C$12/100-Returns!J20*I9*(Returns!J22+Returns!$I$8/10000)/4-$F7*IF(AND(Returns!J20=1,Returns!J24=0),MIN(I8,Returns!$C$6*Returns!$C$11/4),0)/Returns!$C$6-Returns!J21*J9 | K10: =Returns!K20*(1-Returns!K24)*J8*(Returns!K22+$C7/10000)/4+IF(AND(Returns!K20=1,Returns!K24=0),MIN(J8,Returns!$C$6*Returns!$C$11/4),0)+Returns!K21*K8*Returns!$C$12/100-Returns!K20*J9*(Returns!K22+Returns!$I$8/10000)/4-$F7*IF(AND(Returns!K20=1,Returns!K24=0),MIN(J8,Returns!$C$6*Returns!$C$11/4),0)/Returns!$C$6-Returns!K21*K9 | ... W10: =Returns!W20*(1-Returns!W24)*V8*(Returns!W22+$C7/10000)/4+IF(AND(Returns!W20=1,Returns!W24=0),MIN(V8,Returns!$C$6*Returns!$C$11/4),0)+Returns!W21*W8*Returns!$C$12/100-Returns!W20*V9*(Returns!W22+Returns!$I$8/10000)/4-$F7*IF(AND(Returns!W20=1,Returns!W24=0),MIN(V8,Returns!$C$6*Returns!$C$11/4),0)/Returns!$C$6-Returns!W21*W9
B12: Spread offset -100 bps, leverage 1.00x — parameters (spread, leverage, advance rate, financing at close) | C12: =Returns!$C$7+(-100) | D12: 1 | E12: =D12/(1+D12) | F12: =Returns!$C$6*(1-Returns!$D$8)*E12
B13: Loan ending balance (before exit payoff) | C13: =Returns!$C$6 | D13: =IF(Returns!D20=1,C13+Returns!D24*C13*(Returns!D22+$C12/10000)/4-IF(AND(Returns!D20=1,Returns!D24=0),MIN(C13,Returns!$C$6*Returns!$C$11/4),0),0) | E13: =IF(Returns!E20=1,D13+Returns!E24*D13*(Returns!E22+$C12/10000)/4-IF(AND(Returns!E20=1,Returns!E24=0),MIN(D13,Returns!$C$6*Returns!$C$11/4),0),0) | F13: =IF(Returns!F20=1,E13+Returns!F24*E13*(Returns!F22+$C12/10000)/4-IF(AND(Returns!F20=1,Returns!F24=0),MIN(E13,Returns!$C$6*Returns!$C$11/4),0),0) | G13: =IF(Returns!G20=1,F13+Returns!G24*F13*(Returns!G22+$C12/10000)/4-IF(AND(Returns!G20=1,Returns!G24=0),MIN(F13,Returns!$C$6*Returns!$C$11/4),0),0) | H13: =IF(Returns!H20=1,G13+Returns!H24*G13*(Returns!H22+$C12/10000)/4-IF(AND(Returns!H20=1,Returns!H24=0),MIN(G13,Returns!$C$6*Returns!$C$11/4),0),0) | I13: =IF(Returns!I20=1,H13+Returns!I24*H13*(Returns!I22+$C12/10000)/4-IF(AND(Returns!I20=1,Returns!I24=0),MIN(H13,Returns!$C$6*Returns!$C$11/4),0),0) | J13: =IF(Returns!J20=1,I13+Returns!J24*I13*(Returns!J22+$C12/10000)/4-IF(AND(Returns!J20=1,Returns!J24=0),MIN(I13,Returns!$C$6*Returns!$C$11/4),0),0) | K13: =IF(Returns!K20=1,J13+Returns!K24*J13*(Returns!K22+$C12/10000)/4-IF(AND(Returns!K20=1,Returns!K24=0),MIN(J13,Returns!$C$6*Returns!$C$11/4),0),0) | ... W13: =IF(Returns!W20=1,V13+Returns!W24*V13*(Returns!W22+$C12/10000)/4-IF(AND(Returns!W20=1,Returns!W24=0),MIN(V13,Returns!$C$6*Returns!$C$11/4),0),0)
B14: Financing line ending balance (before exit payoff) | C14: =$F12 | D14: =IF(Returns!D20=1,C14-$F12*IF(AND(Returns!D20=1,Returns!D24=0),MIN(C13,Returns!$C$6*Returns!$C$11/4),0)/Returns!$C$6,0) | E14: =IF(Returns!E20=1,D14-$F12*IF(AND(Returns!E20=1,Returns!E24=0),MIN(D13,Returns!$C$6*Returns!$C$11/4),0)/Returns!$C$6,0) | F14: =IF(Returns!F20=1,E14-$F12*IF(AND(Returns!F20=1,Returns!F24=0),MIN(E13,Returns!$C$6*Returns!$C$11/4),0)/Returns!$C$6,0) | G14: =IF(Returns!G20=1,F14-$F12*IF(AND(Returns!G20=1,Returns!G24=0),MIN(F13,Returns!$C$6*Returns!$C$11/4),0)/Returns!$C$6,0) | H14: =IF(Returns!H20=1,G14-$F12*IF(AND(Returns!H20=1,Returns!H24=0),MIN(G13,Returns!$C$6*Returns!$C$11/4),0)/Returns!$C$6,0) | I14: =IF(Returns!I20=1,H14-$F12*IF(AND(Returns!I20=1,Returns!I24=0),MIN(H13,Returns!$C$6*Returns!$C$11/4),0)/Returns!$C$6,0) | J14: =IF(Returns!J20=1,I14-$F12*IF(AND(Returns!J20=1,Returns!J24=0),MIN(I13,Returns!$C$6*Returns!$C$11/4),0)/Returns!$C$6,0) | K14: =IF(Returns!K20=1,J14-$F12*IF(AND(Returns!K20=1,Returns!K24=0),MIN(J13,Returns!$C$6*Returns!$C$11/4),0)/Returns!$C$6,0) | ... W14: =IF(Returns!W20=1,V14-$F12*IF(AND(Returns!W20=1,Returns!W24=0),MIN(V13,Returns!$C$6*Returns!$C$11/4),0)/Returns!$C$6,0)
B15: Levered net cash flow | C15: =-Returns!$C$6*(1-Returns!$D$8)+$F12 | D15: =Returns!D20*(1-Returns!D24)*C13*(Returns!D22+$C12/10000)/4+IF(AND(Returns!D20=1,Returns!D24=0),MIN(C13,Returns!$C$6*Returns!$C$11/4),0)+Returns!D21*D13*Returns!$C$12/100-Returns!D20*C14*(Returns!D22+Returns!$I$8/10000)/4-$F12*IF(AND(Returns!D20=1,Returns!D24=0),MIN(C13,Returns!$C$6*Returns!$C$11/4),0)/Returns!$C$6-Returns!D21*D14 | E15: =Returns!E20*(1-Returns!E24)*D13*(Returns!E22+$C12/10000)/4+IF(AND(Returns!E20=1,Returns!E24=0),MIN(D13,Returns!$C$6*Returns!$C$11/4),0)+Returns!E21*E13*Returns!$C$12/100-Returns!E20*D14*(Returns!E22+Returns!$I$8/10000)/4-$F12*IF(AND(Returns!E20=1,Returns!E24=0),MIN(D13,Returns!$C$6*Returns!$C$11/4),0)/Returns!$C$6-Returns!E21*E14 | F15: =Returns!F20*(1-Returns!F24)*E13*(Returns!F22+$C12/10000)/4+IF(AND(Returns!F20=1,Returns!F24=0),MIN(E13,Returns!$C$6*Returns!$C$11/4),0)+Returns!F21*F13*Returns!$C$12/100-Returns!F20*E14*(Returns!F22+Returns!$I$8/10000)/4-$F12*IF(AND(Returns!F20=1,Returns!F24=0),MIN(E13,Returns!$C$6*Returns!$C$11/4),0)/Returns!$C$6-Returns!F21*F14 | G15: =Returns!G20*(1-Returns!G24)*F13*(Returns!G22+$C12/10000)/4+IF(AND(Returns!G20=1,Returns!G24=0),MIN(F13,Returns!$C$6*Returns!$C$11/4),0)+Returns!G21*G13*Returns!$C$12/100-Returns!G20*F14*(Returns!G22+Returns!$I$8/10000)/4-$F12*IF(AND(Returns!G20=1,Returns!G24=0),MIN(F13,Returns!$C$6*Returns!$C$11/4),0)/Returns!$C$6-Returns!G21*G14 | H15: =Returns!H20*(1-Returns!H24)*G13*(Returns!H22+$C12/10000)/4+IF(AND(Returns!H20=1,Returns!H24=0),MIN(G13,Returns!$C$6*Returns!$C$11/4),0)+Returns!H21*H13*Returns!$C$12/100-Returns!H20*G14*(Returns!H22+Returns!$I$8/10000)/4-$F12*IF(AND(Returns!H20=1,Returns!H24=0),MIN(G13,Returns!$C$6*Returns!$C$11/4),0)/Returns!$C$6-Returns!H21*H14 | I15: =Returns!I20*(1-Returns!I24)*H13*(Returns!I22+$C12/10000)/4+IF(AND(Returns!I20=1,Returns!I24=0),MIN(H13,Returns!$C$6*Returns!$C$11/4),0)+Returns!I21*I13*Returns!$C$12/100-Returns!I20*H14*(Returns!I22+Returns!$I$8/10000)/4-$F12*IF(AND(Returns!I20=1,Returns!I24=0),MIN(H13,Returns!$C$6*Returns!$C$11/4),0)/Returns!$C$6-Returns!I21*I14 | J15: =Returns!J20*(1-Returns!J24)*I13*(Returns!J22+$C12/10000)/4+IF(AND(Returns!J20=1,Returns!J24=0),MIN(I13,Returns!$C$6*Returns!$C$11/4),0)+Returns!J21*J13*Returns!$C$12/100-Returns!J20*I14*(Returns!J22+Returns!$I$8/10000)/4-$F12*IF(AND(Returns!J20=1,Returns!J24=0),MIN(I13,Returns!$C$6*Returns!$C$11/4),0)/Returns!$C$6-Returns!J21*J14 | K15: =Returns!K20*(1-Returns!K24)*J13*(Returns!K22+$C12/10000)/4+IF(AND(Returns!K20=1,Returns!K24=0),MIN(J13,Returns!$C$6*Returns!$C$11/4),0)+Returns!K21*K13*Returns!$C$12/100-Returns!K20*J14*(Returns!K22+Returns!$I$8/10000)/4-$F12*IF(AND(Returns!K20=1,Returns!K24=0),MIN(J13,Returns!$C$6*Returns!$C$11/4),0)/Returns!$C$6-Returns!K21*K14 | ... W15: =Returns!W20*(1-Returns!W24)*V13*(Returns!W22+$C12/10000)/4+IF(AND(Returns!W20=1,Returns!W24=0),MIN(V13,Returns!$C$6*Returns!$C$11/4),0)+Returns!W21*W13*Returns!$C$12/100-Returns!W20*V14*(Returns!W22+Returns!$I$8/10000)/4-$F12*IF(AND(Returns!W20=1,Returns!W24=0),MIN(V13,Returns!$C$6*Returns!$C$11/4),0)/Returns!$C$6-Returns!W21*W14
B17: Spread offset -100 bps, leverage 1.25x — parameters (spread, leverage, advance rate, financing at close) | C17: =Returns!$C$7+(-100) | D17: 1.25 | E17: =D17/(1+D17) | F17: =Returns!$C$6*(1-Returns!$D$8)*E17
B18: Loan ending balance (before exit payoff) | C18: =Returns!$C$6 | D18: =IF(Returns!D20=1,C18+Returns!D24*C18*(Returns!D22+$C17/10000)/4-IF(AND(Returns!D20=1,Returns!D24=0),MIN(C18,Returns!$C$6*Returns!$C$11/4),0),0) | E18: =IF(Returns!E20=1,D18+Returns!E24*D18*(Returns!E22+$C17/10000)/4-IF(AND(Returns!E20=1,Returns!E24=0),MIN(D18,Returns!$C$6*Returns!$C$11/4),0),0) | F18: =IF(Returns!F20=1,E18+Returns!F24*E18*(Returns!F22+$C17/10000)/4-IF(AND(Returns!F20=1,Returns!F24=0),MIN(E18,Returns!$C$6*Returns!$C$11/4),0),0) | G18: =IF(Returns!G20=1,F18+Returns!G24*F18*(Returns!G22+$C17/10000)/4-IF(AND(Returns!G20=1,Returns!G24=0),MIN(F18,Returns!$C$6*Returns!$C$11/4),0),0) | H18: =IF(Returns!H20=1,G18+Returns!H24*G18*(Returns!H22+$C17/10000)/4-IF(AND(Returns!H20=1,Returns!H24=0),MIN(G18,Returns!$C$6*Returns!$C$11/4),0),0) | I18: =IF(Returns!I20=1,H18+Returns!I24*H18*(Returns!I22+$C17/10000)/4-IF(AND(Returns!I20=1,Returns!I24=0),MIN(H18,Returns!$C$6*Returns!$C$11/4),0),0) | J18: =IF(Returns!J20=1,I18+Returns!J24*I18*(Returns!J22+$C17/10000)/4-IF(AND(Returns!J20=1,Returns!J24=0),MIN(I18,Returns!$C$6*Returns!$C$11/4),0),0) | K18: =IF(Returns!K20=1,J18+Returns!K24*J18*(Returns!K22+$C17/10000)/4-IF(AND(Returns!K20=1,Returns!K24=0),MIN(J18,Returns!$C$6*Returns!$C$11/4),0),0) | ... W18: =IF(Returns!W20=1,V18+Returns!W24*V18*(Returns!W22+$C17/10000)/4-IF(AND(Returns!W20=1,Returns!W24=0),MIN(V18,Returns!$C$6*Returns!$C$11/4),0),0)
B19: Financing line ending balance (before exit payoff) | C19: =$F17 | D19: =IF(Returns!D20=1,C19-$F17*IF(AND(Returns!D20=1,Returns!D24=0),MIN(C18,Returns!$C$6*Returns!$C$11/4),0)/Returns!$C$6,0) | E19: =IF(Returns!E20=1,D19-$F17*IF(AND(Returns!E20=1,Returns!E24=0),MIN(D18,Returns!$C$6*Returns!$C$11/4),0)/Returns!$C$6,0) | F19: =IF(Returns!F20=1,E19-$F17*IF(AND(Returns!F20=1,Returns!F24=0),MIN(E18,Returns!$C$6*Returns!$C$11/4),0)/Returns!$C$6,0) | G19: =IF(Returns!G20=1,F19-$F17*IF(AND(Returns!G20=1,Returns!G24=0),MIN(F18,Returns!$C$6*Returns!$C$11/4),0)/Returns!$C$6,0) | H19: =IF(Returns!H20=1,G19-$F17*IF(AND(Returns!H20=1,Returns!H24=0),MIN(G18,Returns!$C$6*Returns!$C$11/4),0)/Returns!$C$6,0) | I19: =IF(Returns!I20=1,H19-$F17*IF(AND(Returns!I20=1,Returns!I24=0),MIN(H18,Returns!$C$6*Returns!$C$11/4),0)/Returns!$C$6,0) | J19: =IF(Returns!J20=1,I19-$F17*IF(AND(Returns!J20=1,Returns!J24=0),MIN(I18,Returns!$C$6*Returns!$C$11/4),0)/Returns!$C$6,0) | K19: =IF(Returns!K20=1,J19-$F17*IF(AND(Returns!K20=1,Returns!K24=0),MIN(J18,Returns!$C$6*Returns!$C$11/4),0)/Returns!$C$6,0) | ... W19: =IF(Returns!W20=1,V19-$F17*IF(AND(Returns!W20=1,Returns!W24=0),MIN(V18,Returns!$C$6*Returns!$C$11/4),0)/Returns!$C$6,0)
B20: Levered net cash flow | C20: =-Returns!$C$6*(1-Returns!$D$8)+$F17 | D20: =Returns!D20*(1-Returns!D24)*C18*(Returns!D22+$C17/10000)/4+IF(AND(Returns!D20=1,Returns!D24=0),MIN(C18,Returns!$C$6*Returns!$C$11/4),0)+Returns!D21*D18*Returns!$C$12/100-Returns!D20*C19*(Returns!D22+Returns!$I$8/10000)/4-$F17*IF(AND(Returns!D20=1,Returns!D24=0),MIN(C18,Returns!$C$6*Returns!$C$11/4),0)/Returns!$C$6-Returns!D21*D19 | E20: =Returns!E20*(1-Returns!E24)*D18*(Returns!E22+$C17/10000)/4+IF(AND(Returns!E20=1,Returns!E24=0),MIN(D18,Returns!$C$6*Returns!$C$11/4),0)+Returns!E21*E18*Returns!$C$12/100-Returns!E20*D19*(Returns!E22+Returns!$I$8/10000)/4-$F17*IF(AND(Returns!E20=1,Returns!E24=0),MIN(D18,Returns!$C$6*Returns!$C$11/4),0)/Returns!$C$6-Returns!E21*E19 | F20: =Returns!F20*(1-Returns!F24)*E18*(Returns!F22+$C17/10000)/4+IF(AND(Returns!F20=1,Returns!F24=0),MIN(E18,Returns!$C$6*Returns!$C$11/4),0)+Returns!F21*F18*Returns!$C$12/100-Returns!F20*E19*(Returns!F22+Returns!$I$8/10000)/4-$F17*IF(AND(Returns!F20=1,Returns!F24=0),MIN(E18,Returns!$C$6*Returns!$C$11/4),0)/Returns!$C$6-Returns!F21*F19 | G20: =Returns!G20*(1-Returns!G24)*F18*(Returns!G22+$C17/10000)/4+IF(AND(Returns!G20=1,Returns!G24=0),MIN(F18,Returns!$C$6*Returns!$C$11/4),0)+Returns!G21*G18*Returns!$C$12/100-Returns!G20*F19*(Returns!G22+Returns!$I$8/10000)/4-$F17*IF(AND(Returns!G20=1,Returns!G24=0),MIN(F18,Returns!$C$6*Returns!$C$11/4),0)/Returns!$C$6-Returns!G21*G19 | H20: =Returns!H20*(1-Returns!H24)*G18*(Returns!H22+$C17/10000)/4+IF(AND(Returns!H20=1,Returns!H24=0),MIN(G18,Returns!$C$6*Returns!$C$11/4),0)+Returns!H21*H18*Returns!$C$12/100-Returns!H20*G19*(Returns!H22+Returns!$I$8/10000)/4-$F17*IF(AND(Returns!H20=1,Returns!H24=0),MIN(G18,Returns!$C$6*Returns!$C$11/4),0)/Returns!$C$6-Returns!H21*H19 | I20: =Returns!I20*(1-Returns!I24)*H18*(Returns!I22+$C17/10000)/4+IF(AND(Returns!I20=1,Returns!I24=0),MIN(H18,Returns!$C$6*Returns!$C$11/4),0)+Returns!I21*I18*Returns!$C$12/100-Returns!I20*H19*(Returns!I22+Returns!$I$8/10000)/4-$F17*IF(AND(Returns!I20=1,Returns!I24=0),MIN(H18,Returns!$C$6*Returns!$C$11/4),0)/Returns!$C$6-Returns!I21*I19 | J20: =Returns!J20*(1-Returns!J24)*I18*(Returns!J22+$C17/10000)/4+IF(AND(Returns!J20=1,Returns!J24=0),MIN(I18,Returns!$C$6*Returns!$C$11/4),0)+Returns!J21*J18*Returns!$C$12/100-Returns!J20*I19*(Returns!J22+Returns!$I$8/10000)/4-$F17*IF(AND(Returns!J20=1,Returns!J24=0),MIN(I18,Returns!$C$6*Returns!$C$11/4),0)/Returns!$C$6-Returns!J21*J19 | K20: =Returns!K20*(1-Returns!K24)*J18*(Returns!K22+$C17/10000)/4+IF(AND(Returns!K20=1,Returns!K24=0),MIN(J18,Returns!$C$6*Returns!$C$11/4),0)+Returns!K21*K18*Returns!$C$12/100-Returns!K20*J19*(Returns!K22+Returns!$I$8/10000)/4-$F17*IF(AND(Returns!K20=1,Returns!K24=0),MIN(J18,Returns!$C$6*Returns!$C$11/4),0)/Returns!$C$6-Returns!K21*K19 | ... W20: =Returns!W20*(1-Returns!W24)*V18*(Returns!W22+$C17/10000)/4+IF(AND(Returns!W20=1,Returns!W24=0),MIN(V18,Returns!$C$6*Returns!$C$11/4),0)+Returns!W21*W18*Returns!$C$12/100-Returns!W20*V19*(Returns!W22+Returns!$I$8/10000)/4-$F17*IF(AND(Returns!W20=1,Returns!W24=0),MIN(V18,Returns!$C$6*Returns!$C$11/4),0)/Returns!$C$6-Returns!W21*W19
B22: Spread offset -50 bps, leverage 0.75x — parameters (spread, leverage, advance rate, financing at close) | C22: =Returns!$C$7+(-50) | D22: 0.75 | E22: =D22/(1+D22) | F22: =Returns!$C$6*(1-Returns!$D$8)*E22
B23: Loan ending balance (before exit payoff) | C23: =Returns!$C$6 | D23: =IF(Returns!D20=1,C23+Returns!D24*C23*(Returns!D22+$C22/10000)/4-IF(AND(Returns!D20=1,Returns!D24=0),MIN(C23,Returns!$C$6*Returns!$C$11/4),0),0) | E23: =IF(Returns!E20=1,D23+Returns!E24*D23*(Returns!E22+$C22/10000)/4-IF(AND(Returns!E20=1,Returns!E24=0),MIN(D23,Returns!$C$6*Returns!$C$11/4),0),0) | F23: =IF(Returns!F20=1,E23+Returns!F24*E23*(Returns!F22+$C22/10000)/4-IF(AND(Returns!F20=1,Returns!F24=0),MIN(E23,Returns!$C$6*Returns!$C$11/4),0),0) | G23: =IF(Returns!G20=1,F23+Returns!G24*F23*(Returns!G22+$C22/10000)/4-IF(AND(Returns!G20=1,Returns!G24=0),MIN(F23,Returns!$C$6*Returns!$C$11/4),0),0) | H23: =IF(Returns!H20=1,G23+Returns!H24*G23*(Returns!H22+$C22/10000)/4-IF(AND(Returns!H20=1,Returns!H24=0),MIN(G23,Returns!$C$6*Returns!$C$11/4),0),0) | I23: =IF(Returns!I20=1,H23+Returns!I24*H23*(Returns!I22+$C22/10000)/4-IF(AND(Returns!I20=1,Returns!I24=0),MIN(H23,Returns!$C$6*Returns!$C$11/4),0),0) | J23: =IF(Returns!J20=1,I23+Returns!J24*I23*(Returns!J22+$C22/10000)/4-IF(AND(Returns!J20=1,Returns!J24=0),MIN(I23,Returns!$C$6*Returns!$C$11/4),0),0) | K23: =IF(Returns!K20=1,J23+Returns!K24*J23*(Returns!K22+$C22/10000)/4-IF(AND(Returns!K20=1,Returns!K24=0),MIN(J23,Returns!$C$6*Returns!$C$11/4),0),0) | ... W23: =IF(Returns!W20=1,V23+Returns!W24*V23*(Returns!W22+$C22/10000)/4-IF(AND(Returns!W20=1,Returns!W24=0),MIN(V23,Returns!$C$6*Returns!$C$11/4),0),0)
B24: Financing line ending balance (before exit payoff) | C24: =$F22 | D24: =IF(Returns!D20=1,C24-$F22*IF(AND(Returns!D20=1,Returns!D24=0),MIN(C23,Returns!$C$6*Returns!$C$11/4),0)/Returns!$C$6,0) | E24: =IF(Returns!E20=1,D24-$F22*IF(AND(Returns!E20=1,Returns!E24=0),MIN(D23,Returns!$C$6*Returns!$C$11/4),0)/Returns!$C$6,0) | F24: =IF(Returns!F20=1,E24-$F22*IF(AND(Returns!F20=1,Returns!F24=0),MIN(E23,Returns!$C$6*Returns!$C$11/4),0)/Returns!$C$6,0) | G24: =IF(Returns!G20=1,F24-$F22*IF(AND(Returns!G20=1,Returns!G24=0),MIN(F23,Returns!$C$6*Returns!$C$11/4),0)/Returns!$C$6,0) | H24: =IF(Returns!H20=1,G24-$F22*IF(AND(Returns!H20=1,Returns!H24=0),MIN(G23,Returns!$C$6*Returns!$C$11/4),0)/Returns!$C$6,0) | I24: =IF(Returns!I20=1,H24-$F22*IF(AND(Returns!I20=1,Returns!I24=0),MIN(H23,Returns!$C$6*Returns!$C$11/4),0)/Returns!$C$6,0) | J24: =IF(Returns!J20=1,I24-$F22*IF(AND(Returns!J20=1,Returns!J24=0),MIN(I23,Returns!$C$6*Returns!$C$11/4),0)/Returns!$C$6,0) | K24: =IF(Returns!K20=1,J24-$F22*IF(AND(Returns!K20=1,Returns!K24=0),MIN(J23,Returns!$C$6*Returns!$C$11/4),0)/Returns!$C$6,0) | ... W24: =IF(Returns!W20=1,V24-$F22*IF(AND(Returns!W20=1,Returns!W24=0),MIN(V23,Returns!$C$6*Returns!$C$11/4),0)/Returns!$C$6,0)
B25: Levered net cash flow | C25: =-Returns!$C$6*(1-Returns!$D$8)+$F22 | D25: =Returns!D20*(1-Returns!D24)*C23*(Returns!D22+$C22/10000)/4+IF(AND(Returns!D20=1,Returns!D24=0),MIN(C23,Returns!$C$6*Returns!$C$11/4),0)+Returns!D21*D23*Returns!$C$12/100-Returns!D20*C24*(Returns!D22+Returns!$I$8/10000)/4-$F22*IF(AND(Returns!D20=1,Returns!D24=0),MIN(C23,Returns!$C$6*Returns!$C$11/4),0)/Returns!$C$6-Returns!D21*D24 | E25: =Returns!E20*(1-Returns!E24)*D23*(Returns!E22+$C22/10000)/4+IF(AND(Returns!E20=1,Returns!E24=0),MIN(D23,Returns!$C$6*Returns!$C$11/4),0)+Returns!E21*E23*Returns!$C$12/100-Returns!E20*D24*(Returns!E22+Returns!$I$8/10000)/4-$F22*IF(AND(Returns!E20=1,Returns!E24=0),MIN(D23,Returns!$C$6*Returns!$C$11/4),0)/Returns!$C$6-Returns!E21*E24 | F25: =Returns!F20*(1-Returns!F24)*E23*(Returns!F22+$C22/10000)/4+IF(AND(Returns!F20=1,Returns!F24=0),MIN(E23,Returns!$C$6*Returns!$C$11/4),0)+Returns!F21*F23*Returns!$C$12/100-Returns!F20*E24*(Returns!F22+Returns!$I$8/10000)/4-$F22*IF(AND(Returns!F20=1,Returns!F24=0),MIN(E23,Returns!$C$6*Returns!$C$11/4),0)/Returns!$C$6-Returns!F21*F24 | G25: =Returns!G20*(1-Returns!G24)*F23*(Returns!G22+$C22/10000)/4+IF(AND(Returns!G20=1,Returns!G24=0),MIN(F23,Returns!$C$6*Returns!$C$11/4),0)+Returns!G21*G23*Returns!$C$12/100-Returns!G20*F24*(Returns!G22+Returns!$I$8/10000)/4-$F22*IF(AND(Returns!G20=1,Returns!G24=0),MIN(F23,Returns!$C$6*Returns!$C$11/4),0)/Returns!$C$6-Returns!G21*G24 | H25: =Returns!H20*(1-Returns!H24)*G23*(Returns!H22+$C22/10000)/4+IF(AND(Returns!H20=1,Returns!H24=0),MIN(G23,Returns!$C$6*Returns!$C$11/4),0)+Returns!H21*H23*Returns!$C$12/100-Returns!H20*G24*(Returns!H22+Returns!$I$8/10000)/4-$F22*IF(AND(Returns!H20=1,Returns!H24=0),MIN(G23,Returns!$C$6*Returns!$C$11/4),0)/Returns!$C$6-Returns!H21*H24 | I25: =Returns!I20*(1-Returns!I24)*H23*(Returns!I22+$C22/10000)/4+IF(AND(Returns!I20=1,Returns!I24=0),MIN(H23,Returns!$C$6*Returns!$C$11/4),0)+Returns!I21*I23*Returns!$C$12/100-Returns!I20*H24*(Returns!I22+Returns!$I$8/10000)/4-$F22*IF(AND(Returns!I20=1,Returns!I24=0),MIN(H23,Returns!$C$6*Returns!$C$11/4),0)/Returns!$C$6-Returns!I21*I24 | J25: =Returns!J20*(1-Returns!J24)*I23*(Returns!J22+$C22/10000)/4+IF(AND(Returns!J20=1,Returns!J24=0),MIN(I23,Returns!$C$6*Returns!$C$11/4),0)+Returns!J21*J23*Returns!$C$12/100-Returns!J20*I24*(Returns!J22+Returns!$I$8/10000)/4-$F22*IF(AND(Returns!J20=1,Returns!J24=0),MIN(I23,Returns!$C$6*Returns!$C$11/4),0)/Returns!$C$6-Returns!J21*J24 | K25: =Returns!K20*(1-Returns!K24)*J23*(Returns!K22+$C22/10000)/4+IF(AND(Returns!K20=1,Returns!K24=0),MIN(J23,Returns!$C$6*Returns!$C$11/4),0)+Returns!K21*K23*Returns!$C$12/100-Returns!K20*J24*(Returns!K22+Returns!$I$8/10000)/4-$F22*IF(AND(Returns!K20=1,Returns!K24=0),MIN(J23,Returns!$C$6*Returns!$C$11/4),0)/Returns!$C$6-Returns!K21*K24 | ... W25: =Returns!W20*(1-Returns!W24)*V23*(Returns!W22+$C22/10000)/4+IF(AND(Returns!W20=1,Returns!W24=0),MIN(V23,Returns!$C$6*Returns!$C$11/4),0)+Returns!W21*W23*Returns!$C$12/100-Returns!W20*V24*(Returns!W22+Returns!$I$8/10000)/4-$F22*IF(AND(Returns!W20=1,Returns!W24=0),MIN(V23,Returns!$C$6*Returns!$C$11/4),0)/Returns!$C$6-Returns!W21*W24
B27: Spread offset -50 bps, leverage 1.00x — parameters (spread, leverage, advance rate, financing at close) | C27: =Returns!$C$7+(-50) | D27: 1 | E27: =D27/(1+D27) | F27: =Returns!$C$6*(1-Returns!$D$8)*E27
B28: Loan ending balance (before exit payoff) | C28: =Returns!$C$6 | D28: =IF(Returns!D20=1,C28+Returns!D24*C28*(Returns!D22+$C27/10000)/4-IF(AND(Returns!D20=1,Returns!D24=0),MIN(C28,Returns!$C$6*Returns!$C$11/4),0),0) | E28: =IF(Returns!E20=1,D28+Returns!E24*D28*(Returns!E22+$C27/10000)/4-IF(AND(Returns!E20=1,Returns!E24=0),MIN(D28,Returns!$C$6*Returns!$C$11/4),0),0) | F28: =IF(Returns!F20=1,E28+Returns!F24*E28*(Returns!F22+$C27/10000)/4-IF(AND(Returns!F20=1,Returns!F24=0),MIN(E28,Returns!$C$6*Returns!$C$11/4),0),0) | G28: =IF(Returns!G20=1,F28+Returns!G24*F28*(Returns!G22+$C27/10000)/4-IF(AND(Returns!G20=1,Returns!G24=0),MIN(F28,Returns!$C$6*Returns!$C$11/4),0),0) | H28: =IF(Returns!H20=1,G28+Returns!H24*G28*(Returns!H22+$C27/10000)/4-IF(AND(Returns!H20=1,Returns!H24=0),MIN(G28,Returns!$C$6*Returns!$C$11/4),0),0) | I28: =IF(Returns!I20=1,H28+Returns!I24*H28*(Returns!I22+$C27/10000)/4-IF(AND(Returns!I20=1,Returns!I24=0),MIN(H28,Returns!$C$6*Returns!$C$11/4),0),0) | J28: =IF(Returns!J20=1,I28+Returns!J24*I28*(Returns!J22+$C27/10000)/4-IF(AND(Returns!J20=1,Returns!J24=0),MIN(I28,Returns!$C$6*Returns!$C$11/4),0),0) | K28: =IF(Returns!K20=1,J28+Returns!K24*J28*(Returns!K22+$C27/10000)/4-IF(AND(Returns!K20=1,Returns!K24=0),MIN(J28,Returns!$C$6*Returns!$C$11/4),0),0) | ... W28: =IF(Returns!W20=1,V28+Returns!W24*V28*(Returns!W22+$C27/10000)/4-IF(AND(Returns!W20=1,Returns!W24=0),MIN(V28,Returns!$C$6*Returns!$C$11/4),0),0)
B29: Financing line ending balance (before exit payoff) | C29: =$F27 | D29: =IF(Returns!D20=1,C29-$F27*IF(AND(Returns!D20=1,Returns!D24=0),MIN(C28,Returns!$C$6*Returns!$C$11/4),0)/Returns!$C$6,0) | E29: =IF(Returns!E20=1,D29-$F27*IF(AND(Returns!E20=1,Returns!E24=0),MIN(D28,Returns!$C$6*Returns!$C$11/4),0)/Returns!$C$6,0) | F29: =IF(Returns!F20=1,E29-$F27*IF(AND(Returns!F20=1,Returns!F24=0),MIN(E28,Returns!$C$6*Returns!$C$11/4),0)/Returns!$C$6,0) | G29: =IF(Returns!G20=1,F29-$F27*IF(AND(Returns!G20=1,Returns!G24=0),MIN(F28,Returns!$C$6*Returns!$C$11/4),0)/Returns!$C$6,0) | H29: =IF(Returns!H20=1,G29-$F27*IF(AND(Returns!H20=1,Returns!H24=0),MIN(G28,Returns!$C$6*Returns!$C$11/4),0)/Returns!$C$6,0) | I29: =IF(Returns!I20=1,H29-$F27*IF(AND(Returns!I20=1,Returns!I24=0),MIN(H28,Returns!$C$6*Returns!$C$11/4),0)/Returns!$C$6,0) | J29: =IF(Returns!J20=1,I29-$F27*IF(AND(Returns!J20=1,Returns!J24=0),MIN(I28,Returns!$C$6*Returns!$C$11/4),0)/Returns!$C$6,0) | K29: =IF(Returns!K20=1,J29-$F27*IF(AND(Returns!K20=1,Returns!K24=0),MIN(J28,Returns!$C$6*Returns!$C$11/4),0)/Returns!$C$6,0) | ... W29: =IF(Returns!W20=1,V29-$F27*IF(AND(Returns!W20=1,Returns!W24=0),MIN(V28,Returns!$C$6*Returns!$C$11/4),0)/Returns!$C$6,0)
B30: Levered net cash flow | C30: =-Returns!$C$6*(1-Returns!$D$8)+$F27 | D30: =Returns!D20*(1-Returns!D24)*C28*(Returns!D22+$C27/10000)/4+IF(AND(Returns!D20=1,Returns!D24=0),MIN(C28,Returns!$C$6*Returns!$C$11/4),0)+Returns!D21*D28*Returns!$C$12/100-Returns!D20*C29*(Returns!D22+Returns!$I$8/10000)/4-$F27*IF(AND(Returns!D20=1,Returns!D24=0),MIN(C28,Returns!$C$6*Returns!$C$11/4),0)/Returns!$C$6-Returns!D21*D29 | E30: =Returns!E20*(1-Returns!E24)*D28*(Returns!E22+$C27/10000)/4+IF(AND(Returns!E20=1,Returns!E24=0),MIN(D28,Returns!$C$6*Returns!$C$11/4),0)+Returns!E21*E28*Returns!$C$12/100-Returns!E20*D29*(Returns!E22+Returns!$I$8/10000)/4-$F27*IF(AND(Returns!E20=1,Returns!E24=0),MIN(D28,Returns!$C$6*Returns!$C$11/4),0)/Returns!$C$6-Returns!E21*E29 | F30: =Returns!F20*(1-Returns!F24)*E28*(Returns!F22+$C27/10000)/4+IF(AND(Returns!F20=1,Returns!F24=0),MIN(E28,Returns!$C$6*Returns!$C$11/4),0)+Returns!F21*F28*Returns!$C$12/100-Returns!F20*E29*(Returns!F22+Returns!$I$8/10000)/4-$F27*IF(AND(Returns!F20=1,Returns!F24=0),MIN(E28,Returns!$C$6*Returns!$C$11/4),0)/Returns!$C$6-Returns!F21*F29 | G30: =Returns!G20*(1-Returns!G24)*F28*(Returns!G22+$C27/10000)/4+IF(AND(Returns!G20=1,Returns!G24=0),MIN(F28,Returns!$C$6*Returns!$C$11/4),0)+Returns!G21*G28*Returns!$C$12/100-Returns!G20*F29*(Returns!G22+Returns!$I$8/10000)/4-$F27*IF(AND(Returns!G20=1,Returns!G24=0),MIN(F28,Returns!$C$6*Returns!$C$11/4),0)/Returns!$C$6-Returns!G21*G29 | H30: =Returns!H20*(1-Returns!H24)*G28*(Returns!H22+$C27/10000)/4+IF(AND(Returns!H20=1,Returns!H24=0),MIN(G28,Returns!$C$6*Returns!$C$11/4),0)+Returns!H21*H28*Returns!$C$12/100-Returns!H20*G29*(Returns!H22+Returns!$I$8/10000)/4-$F27*IF(AND(Returns!H20=1,Returns!H24=0),MIN(G28,Returns!$C$6*Returns!$C$11/4),0)/Returns!$C$6-Returns!H21*H29 | I30: =Returns!I20*(1-Returns!I24)*H28*(Returns!I22+$C27/10000)/4+IF(AND(Returns!I20=1,Returns!I24=0),MIN(H28,Returns!$C$6*Returns!$C$11/4),0)+Returns!I21*I28*Returns!$C$12/100-Returns!I20*H29*(Returns!I22+Returns!$I$8/10000)/4-$F27*IF(AND(Returns!I20=1,Returns!I24=0),MIN(H28,Returns!$C$6*Returns!$C$11/4),0)/Returns!$C$6-Returns!I21*I29 | J30: =Returns!J20*(1-Returns!J24)*I28*(Returns!J22+$C27/10000)/4+IF(AND(Returns!J20=1,Returns!J24=0),MIN(I28,Returns!$C$6*Returns!$C$11/4),0)+Returns!J21*J28*Returns!$C$12/100-Returns!J20*I29*(Returns!J22+Returns!$I$8/10000)/4-$F27*IF(AND(Returns!J20=1,Returns!J24=0),MIN(I28,Returns!$C$6*Returns!$C$11/4),0)/Returns!$C$6-Returns!J21*J29 | K30: =Returns!K20*(1-Returns!K24)*J28*(Returns!K22+$C27/10000)/4+IF(AND(Returns!K20=1,Returns!K24=0),MIN(J28,Returns!$C$6*Returns!$C$11/4),0)+Returns!K21*K28*Returns!$C$12/100-Returns!K20*J29*(Returns!K22+Returns!$I$8/10000)/4-$F27*IF(AND(Returns!K20=1,Returns!K24=0),MIN(J28,Returns!$C$6*Returns!$C$11/4),0)/Returns!$C$6-Returns!K21*K29 | ... W30: =Returns!W20*(1-Returns!W24)*V28*(Returns!W22+$C27/10000)/4+IF(AND(Returns!W20=1,Returns!W24=0),MIN(V28,Returns!$C$6*Returns!$C$11/4),0)+Returns!W21*W28*Returns!$C$12/100-Returns!W20*V29*(Returns!W22+Returns!$I$8/10000)/4-$F27*IF(AND(Returns!W20=1,Returns!W24=0),MIN(V28,Returns!$C$6*Returns!$C$11/4),0)/Returns!$C$6-Returns!W21*W29
B32: Spread offset -50 bps, leverage 1.25x — parameters (spread, leverage, advance rate, financing at close) | C32: =Returns!$C$7+(-50) | D32: 1.25 | E32: =D32/(1+D32) | F32: =Returns!$C$6*(1-Returns!$D$8)*E32
B33: Loan ending balance (before exit payoff) | C33: =Returns!$C$6 | D33: =IF(Returns!D20=1,C33+Returns!D24*C33*(Returns!D22+$C32/10000)/4-IF(AND(Returns!D20=1,Returns!D24=0),MIN(C33,Returns!$C$6*Returns!$C$11/4),0),0) | E33: =IF(Returns!E20=1,D33+Returns!E24*D33*(Returns!E22+$C32/10000)/4-IF(AND(Returns!E20=1,Returns!E24=0),MIN(D33,Returns!$C$6*Returns!$C$11/4),0),0) | F33: =IF(Returns!F20=1,E33+Returns!F24*E33*(Returns!F22+$C32/10000)/4-IF(AND(Returns!F20=1,Returns!F24=0),MIN(E33,Returns!$C$6*Returns!$C$11/4),0),0) | G33: =IF(Returns!G20=1,F33+Returns!G24*F33*(Returns!G22+$C32/10000)/4-IF(AND(Returns!G20=1,Returns!G24=0),MIN(F33,Returns!$C$6*Returns!$C$11/4),0),0) | H33: =IF(Returns!H20=1,G33+Returns!H24*G33*(Returns!H22+$C32/10000)/4-IF(AND(Returns!H20=1,Returns!H24=0),MIN(G33,Returns!$C$6*Returns!$C$11/4),0),0) | I33: =IF(Returns!I20=1,H33+Returns!I24*H33*(Returns!I22+$C32/10000)/4-IF(AND(Returns!I20=1,Returns!I24=0),MIN(H33,Returns!$C$6*Returns!$C$11/4),0),0) | J33: =IF(Returns!J20=1,I33+Returns!J24*I33*(Returns!J22+$C32/10000)/4-IF(AND(Returns!J20=1,Returns!J24=0),MIN(I33,Returns!$C$6*Returns!$C$11/4),0),0) | K33: =IF(Returns!K20=1,J33+Returns!K24*J33*(Returns!K22+$C32/10000)/4-IF(AND(Returns!K20=1,Returns!K24=0),MIN(J33,Returns!$C$6*Returns!$C$11/4),0),0) | ... W33: =IF(Returns!W20=1,V33+Returns!W24*V33*(Returns!W22+$C32/10000)/4-IF(AND(Returns!W20=1,Returns!W24=0),MIN(V33,Returns!$C$6*Returns!$C$11/4),0),0)
B34: Financing line ending balance (before exit payoff) | C34: =$F32 | D34: =IF(Returns!D20=1,C34-$F32*IF(AND(Returns!D20=1,Returns!D24=0),MIN(C33,Returns!$C$6*Returns!$C$11/4),0)/Returns!$C$6,0) | E34: =IF(Returns!E20=1,D34-$F32*IF(AND(Returns!E20=1,Returns!E24=0),MIN(D33,Returns!$C$6*Returns!$C$11/4),0)/Returns!$C$6,0) | F34: =IF(Returns!F20=1,E34-$F32*IF(AND(Returns!F20=1,Returns!F24=0),MIN(E33,Returns!$C$6*Returns!$C$11/4),0)/Returns!$C$6,0) | G34: =IF(Returns!G20=1,F34-$F32*IF(AND(Returns!G20=1,Returns!G24=0),MIN(F33,Returns!$C$6*Returns!$C$11/4),0)/Returns!$C$6,0) | H34: =IF(Returns!H20=1,G34-$F32*IF(AND(Returns!H20=1,Returns!H24=0),MIN(G33,Returns!$C$6*Returns!$C$11/4),0)/Returns!$C$6,0) | I34: =IF(Returns!I20=1,H34-$F32*IF(AND(Returns!I20=1,Returns!I24=0),MIN(H33,Returns!$C$6*Returns!$C$11/4),0)/Returns!$C$6,0) | J34: =IF(Returns!J20=1,I34-$F32*IF(AND(Returns!J20=1,Returns!J24=0),MIN(I33,Returns!$C$6*Returns!$C$11/4),0)/Returns!$C$6,0) | K34: =IF(Returns!K20=1,J34-$F32*IF(AND(Returns!K20=1,Returns!K24=0),MIN(J33,Returns!$C$6*Returns!$C$11/4),0)/Returns!$C$6,0) | ... W34: =IF(Returns!W20=1,V34-$F32*IF(AND(Returns!W20=1,Returns!W24=0),MIN(V33,Returns!$C$6*Returns!$C$11/4),0)/Returns!$C$6,0)
B35: Levered net cash flow | C35: =-Returns!$C$6*(1-Returns!$D$8)+$F32 | D35: =Returns!D20*(1-Returns!D24)*C33*(Returns!D22+$C32/10000)/4+IF(AND(Returns!D20=1,Returns!D24=0),MIN(C33,Returns!$C$6*Returns!$C$11/4),0)+Returns!D21*D33*Returns!$C$12/100-Returns!D20*C34*(Returns!D22+Returns!$I$8/10000)/4-$F32*IF(AND(Returns!D20=1,Returns!D24=0),MIN(C33,Returns!$C$6*Returns!$C$11/4),0)/Returns!$C$6-Returns!D21*D34 | E35: =Returns!E20*(1-Returns!E24)*D33*(Returns!E22+$C32/10000)/4+IF(AND(Returns!E20=1,Returns!E24=0),MIN(D33,Returns!$C$6*Returns!$C$11/4),0)+Returns!E21*E33*Returns!$C$12/100-Returns!E20*D34*(Returns!E22+Returns!$I$8/10000)/4-$F32*IF(AND(Returns!E20=1,Returns!E24=0),MIN(D33,Returns!$C$6*Returns!$C$11/4),0)/Returns!$C$6-Returns!E21*E34 | F35: =Returns!F20*(1-Returns!F24)*E33*(Returns!F22+$C32/10000)/4+IF(AND(Returns!F20=1,Returns!F24=0),MIN(E33,Returns!$C$6*Returns!$C$11/4),0)+Returns!F21*F33*Returns!$C$12/100-Returns!F20*E34*(Returns!F22+Returns!$I$8/10000)/4-$F32*IF(AND(Returns!F20=1,Returns!F24=0),MIN(E33,Returns!$C$6*Returns!$C$11/4),0)/Returns!$C$6-Returns!F21*F34 | G35: =Returns!G20*(1-Returns!G24)*F33*(Returns!G22+$C32/10000)/4+IF(AND(Returns!G20=1,Returns!G24=0),MIN(F33,Returns!$C$6*Returns!$C$11/4),0)+Returns!G21*G33*Returns!$C$12/100-Returns!G20*F34*(Returns!G22+Returns!$I$8/10000)/4-$F32*IF(AND(Returns!G20=1,Returns!G24=0),MIN(F33,Returns!$C$6*Returns!$C$11/4),0)/Returns!$C$6-Returns!G21*G34 | H35: =Returns!H20*(1-Returns!H24)*G33*(Returns!H22+$C32/10000)/4+IF(AND(Returns!H20=1,Returns!H24=0),MIN(G33,Returns!$C$6*Returns!$C$11/4),0)+Returns!H21*H33*Returns!$C$12/100-Returns!H20*G34*(Returns!H22+Returns!$I$8/10000)/4-$F32*IF(AND(Returns!H20=1,Returns!H24=0),MIN(G33,Returns!$C$6*Returns!$C$11/4),0)/Returns!$C$6-Returns!H21*H34 | I35: =Returns!I20*(1-Returns!I24)*H33*(Returns!I22+$C32/10000)/4+IF(AND(Returns!I20=1,Returns!I24=0),MIN(H33,Returns!$C$6*Returns!$C$11/4),0)+Returns!I21*I33*Returns!$C$12/100-Returns!I20*H34*(Returns!I22+Returns!$I$8/10000)/4-$F32*IF(AND(Returns!I20=1,Returns!I24=0),MIN(H33,Returns!$C$6*Returns!$C$11/4),0)/Returns!$C$6-Returns!I21*I34 | J35: =Returns!J20*(1-Returns!J24)*I33*(Returns!J22+$C32/10000)/4+IF(AND(Returns!J20=1,Returns!J24=0),MIN(I33,Returns!$C$6*Returns!$C$11/4),0)+Returns!J21*J33*Returns!$C$12/100-Returns!J20*I34*(Returns!J22+Returns!$I$8/10000)/4-$F32*IF(AND(Returns!J20=1,Returns!J24=0),MIN(I33,Returns!$C$6*Returns!$C$11/4),0)/Returns!$C$6-Returns!J21*J34 | K35: =Returns!K20*(1-Returns!K24)*J33*(Returns!K22+$C32/10000)/4+IF(AND(Returns!K20=1,Returns!K24=0),MIN(J33,Returns!$C$6*Returns!$C$11/4),0)+Returns!K21*K33*Returns!$C$12/100-Returns!K20*J34*(Returns!K22+Returns!$I$8/10000)/4-$F32*IF(AND(Returns!K20=1,Returns!K24=0),MIN(J33,Returns!$C$6*Returns!$C$11/4),0)/Returns!$C$6-Returns!K21*K34 | ... W35: =Returns!W20*(1-Returns!W24)*V33*(Returns!W22+$C32/10000)/4+IF(AND(Returns!W20=1,Returns!W24=0),MIN(V33,Returns!$C$6*Returns!$C$11/4),0)+Returns!W21*W33*Returns!$C$12/100-Returns!W20*V34*(Returns!W22+Returns!$I$8/10000)/4-$F32*IF(AND(Returns!W20=1,Returns!W24=0),MIN(V33,Returns!$C$6*Returns!$C$11/4),0)/Returns!$C$6-Returns!W21*W34
B37: Spread offset +0 bps, leverage 0.75x — parameters (spread, leverage, advance rate, financing at close) | C37: =Returns!$C$7+(0) | D37: 0.75 | E37: =D37/(1+D37) | F37: =Returns!$C$6*(1-Returns!$D$8)*E37
B38: Loan ending balance (before exit payoff) | C38: =Returns!$C$6 | D38: =IF(Returns!D20=1,C38+Returns!D24*C38*(Returns!D22+$C37/10000)/4-IF(AND(Returns!D20=1,Returns!D24=0),MIN(C38,Returns!$C$6*Returns!$C$11/4),0),0) | E38: =IF(Returns!E20=1,D38+Returns!E24*D38*(Returns!E22+$C37/10000)/4-IF(AND(Returns!E20=1,Returns!E24=0),MIN(D38,Returns!$C$6*Returns!$C$11/4),0),0) | F38: =IF(Returns!F20=1,E38+Returns!F24*E38*(Returns!F22+$C37/10000)/4-IF(AND(Returns!F20=1,Returns!F24=0),MIN(E38,Returns!$C$6*Returns!$C$11/4),0),0) | G38: =IF(Returns!G20=1,F38+Returns!G24*F38*(Returns!G22+$C37/10000)/4-IF(AND(Returns!G20=1,Returns!G24=0),MIN(F38,Returns!$C$6*Returns!$C$11/4),0),0) | H38: =IF(Returns!H20=1,G38+Returns!H24*G38*(Returns!H22+$C37/10000)/4-IF(AND(Returns!H20=1,Returns!H24=0),MIN(G38,Returns!$C$6*Returns!$C$11/4),0),0) | I38: =IF(Returns!I20=1,H38+Returns!I24*H38*(Returns!I22+$C37/10000)/4-IF(AND(Returns!I20=1,Returns!I24=0),MIN(H38,Returns!$C$6*Returns!$C$11/4),0),0) | J38: =IF(Returns!J20=1,I38+Returns!J24*I38*(Returns!J22+$C37/10000)/4-IF(AND(Returns!J20=1,Returns!J24=0),MIN(I38,Returns!$C$6*Returns!$C$11/4),0),0) | K38: =IF(Returns!K20=1,J38+Returns!K24*J38*(Returns!K22+$C37/10000)/4-IF(AND(Returns!K20=1,Returns!K24=0),MIN(J38,Returns!$C$6*Returns!$C$11/4),0),0) | ... W38: =IF(Returns!W20=1,V38+Returns!W24*V38*(Returns!W22+$C37/10000)/4-IF(AND(Returns!W20=1,Returns!W24=0),MIN(V38,Returns!$C$6*Returns!$C$11/4),0),0)
B39: Financing line ending balance (before exit payoff) | C39: =$F37 | D39: =IF(Returns!D20=1,C39-$F37*IF(AND(Returns!D20=1,Returns!D24=0),MIN(C38,Returns!$C$6*Returns!$C$11/4),0)/Returns!$C$6,0) | E39: =IF(Returns!E20=1,D39-$F37*IF(AND(Returns!E20=1,Returns!E24=0),MIN(D38,Returns!$C$6*Returns!$C$11/4),0)/Returns!$C$6,0) | F39: =IF(Returns!F20=1,E39-$F37*IF(AND(Returns!F20=1,Returns!F24=0),MIN(E38,Returns!$C$6*Returns!$C$11/4),0)/Returns!$C$6,0) | G39: =IF(Returns!G20=1,F39-$F37*IF(AND(Returns!G20=1,Returns!G24=0),MIN(F38,Returns!$C$6*Returns!$C$11/4),0)/Returns!$C$6,0) | H39: =IF(Returns!H20=1,G39-$F37*IF(AND(Returns!H20=1,Returns!H24=0),MIN(G38,Returns!$C$6*Returns!$C$11/4),0)/Returns!$C$6,0) | I39: =IF(Returns!I20=1,H39-$F37*IF(AND(Returns!I20=1,Returns!I24=0),MIN(H38,Returns!$C$6*Returns!$C$11/4),0)/Returns!$C$6,0) | J39: =IF(Returns!J20=1,I39-$F37*IF(AND(Returns!J20=1,Returns!J24=0),MIN(I38,Returns!$C$6*Returns!$C$11/4),0)/Returns!$C$6,0) | K39: =IF(Returns!K20=1,J39-$F37*IF(AND(Returns!K20=1,Returns!K24=0),MIN(J38,Returns!$C$6*Returns!$C$11/4),0)/Returns!$C$6,0) | ... W39: =IF(Returns!W20=1,V39-$F37*IF(AND(Returns!W20=1,Returns!W24=0),MIN(V38,Returns!$C$6*Returns!$C$11/4),0)/Returns!$C$6,0)
B40: Levered net cash flow | C40: =-Returns!$C$6*(1-Returns!$D$8)+$F37 | D40: =Returns!D20*(1-Returns!D24)*C38*(Returns!D22+$C37/10000)/4+IF(AND(Returns!D20=1,Returns!D24=0),MIN(C38,Returns!$C$6*Returns!$C$11/4),0)+Returns!D21*D38*Returns!$C$12/100-Returns!D20*C39*(Returns!D22+Returns!$I$8/10000)/4-$F37*IF(AND(Returns!D20=1,Returns!D24=0),MIN(C38,Returns!$C$6*Returns!$C$11/4),0)/Returns!$C$6-Returns!D21*D39 | E40: =Returns!E20*(1-Returns!E24)*D38*(Returns!E22+$C37/10000)/4+IF(AND(Returns!E20=1,Returns!E24=0),MIN(D38,Returns!$C$6*Returns!$C$11/4),0)+Returns!E21*E38*Returns!$C$12/100-Returns!E20*D39*(Returns!E22+Returns!$I$8/10000)/4-$F37*IF(AND(Returns!E20=1,Returns!E24=0),MIN(D38,Returns!$C$6*Returns!$C$11/4),0)/Returns!$C$6-Returns!E21*E39 | F40: =Returns!F20*(1-Returns!F24)*E38*(Returns!F22+$C37/10000)/4+IF(AND(Returns!F20=1,Returns!F24=0),MIN(E38,Returns!$C$6*Returns!$C$11/4),0)+Returns!F21*F38*Returns!$C$12/100-Returns!F20*E39*(Returns!F22+Returns!$I$8/10000)/4-$F37*IF(AND(Returns!F20=1,Returns!F24=0),MIN(E38,Returns!$C$6*Returns!$C$11/4),0)/Returns!$C$6-Returns!F21*F39 | G40: =Returns!G20*(1-Returns!G24)*F38*(Returns!G22+$C37/10000)/4+IF(AND(Returns!G20=1,Returns!G24=0),MIN(F38,Returns!$C$6*Returns!$C$11/4),0)+Returns!G21*G38*Returns!$C$12/100-Returns!G20*F39*(Returns!G22+Returns!$I$8/10000)/4-$F37*IF(AND(Returns!G20=1,Returns!G24=0),MIN(F38,Returns!$C$6*Returns!$C$11/4),0)/Returns!$C$6-Returns!G21*G39 | H40: =Returns!H20*(1-Returns!H24)*G38*(Returns!H22+$C37/10000)/4+IF(AND(Returns!H20=1,Returns!H24=0),MIN(G38,Returns!$C$6*Returns!$C$11/4),0)+Returns!H21*H38*Returns!$C$12/100-Returns!H20*G39*(Returns!H22+Returns!$I$8/10000)/4-$F37*IF(AND(Returns!H20=1,Returns!H24=0),MIN(G38,Returns!$C$6*Returns!$C$11/4),0)/Returns!$C$6-Returns!H21*H39 | I40: =Returns!I20*(1-Returns!I24)*H38*(Returns!I22+$C37/10000)/4+IF(AND(Returns!I20=1,Returns!I24=0),MIN(H38,Returns!$C$6*Returns!$C$11/4),0)+Returns!I21*I38*Returns!$C$12/100-Returns!I20*H39*(Returns!I22+Returns!$I$8/10000)/4-$F37*IF(AND(Returns!I20=1,Returns!I24=0),MIN(H38,Returns!$C$6*Returns!$C$11/4),0)/Returns!$C$6-Returns!I21*I39 | J40: =Returns!J20*(1-Returns!J24)*I38*(Returns!J22+$C37/10000)/4+IF(AND(Returns!J20=1,Returns!J24=0),MIN(I38,Returns!$C$6*Returns!$C$11/4),0)+Returns!J21*J38*Returns!$C$12/100-Returns!J20*I39*(Returns!J22+Returns!$I$8/10000)/4-$F37*IF(AND(Returns!J20=1,Returns!J24=0),MIN(I38,Returns!$C$6*Returns!$C$11/4),0)/Returns!$C$6-Returns!J21*J39 | K40: =Returns!K20*(1-Returns!K24)*J38*(Returns!K22+$C37/10000)/4+IF(AND(Returns!K20=1,Returns!K24=0),MIN(J38,Returns!$C$6*Returns!$C$11/4),0)+Returns!K21*K38*Returns!$C$12/100-Returns!K20*J39*(Returns!K22+Returns!$I$8/10000)/4-$F37*IF(AND(Returns!K20=1,Returns!K24=0),MIN(J38,Returns!$C$6*Returns!$C$11/4),0)/Returns!$C$6-Returns!K21*K39 | ... W40: =Returns!W20*(1-Returns!W24)*V38*(Returns!W22+$C37/10000)/4+IF(AND(Returns!W20=1,Returns!W24=0),MIN(V38,Returns!$C$6*Returns!$C$11/4),0)+Returns!W21*W38*Returns!$C$12/100-Returns!W20*V39*(Returns!W22+Returns!$I$8/10000)/4-$F37*IF(AND(Returns!W20=1,Returns!W24=0),MIN(V38,Returns!$C$6*Returns!$C$11/4),0)/Returns!$C$6-Returns!W21*W39
B42: Spread offset +0 bps, leverage 1.00x — parameters (spread, leverage, advance rate, financing at close) | C42: =Returns!$C$7+(0) | D42: 1 | E42: =D42/(1+D42) | F42: =Returns!$C$6*(1-Returns!$D$8)*E42
B43: Loan ending balance (before exit payoff) | C43: =Returns!$C$6 | D43: =IF(Returns!D20=1,C43+Returns!D24*C43*(Returns!D22+$C42/10000)/4-IF(AND(Returns!D20=1,Returns!D24=0),MIN(C43,Returns!$C$6*Returns!$C$11/4),0),0) | E43: =IF(Returns!E20=1,D43+Returns!E24*D43*(Returns!E22+$C42/10000)/4-IF(AND(Returns!E20=1,Returns!E24=0),MIN(D43,Returns!$C$6*Returns!$C$11/4),0),0) | F43: =IF(Returns!F20=1,E43+Returns!F24*E43*(Returns!F22+$C42/10000)/4-IF(AND(Returns!F20=1,Returns!F24=0),MIN(E43,Returns!$C$6*Returns!$C$11/4),0),0) | G43: =IF(Returns!G20=1,F43+Returns!G24*F43*(Returns!G22+$C42/10000)/4-IF(AND(Returns!G20=1,Returns!G24=0),MIN(F43,Returns!$C$6*Returns!$C$11/4),0),0) | H43: =IF(Returns!H20=1,G43+Returns!H24*G43*(Returns!H22+$C42/10000)/4-IF(AND(Returns!H20=1,Returns!H24=0),MIN(G43,Returns!$C$6*Returns!$C$11/4),0),0) | I43: =IF(Returns!I20=1,H43+Returns!I24*H43*(Returns!I22+$C42/10000)/4-IF(AND(Returns!I20=1,Returns!I24=0),MIN(H43,Returns!$C$6*Returns!$C$11/4),0),0) | J43: =IF(Returns!J20=1,I43+Returns!J24*I43*(Returns!J22+$C42/10000)/4-IF(AND(Returns!J20=1,Returns!J24=0),MIN(I43,Returns!$C$6*Returns!$C$11/4),0),0) | K43: =IF(Returns!K20=1,J43+Returns!K24*J43*(Returns!K22+$C42/10000)/4-IF(AND(Returns!K20=1,Returns!K24=0),MIN(J43,Returns!$C$6*Returns!$C$11/4),0),0) | ... W43: =IF(Returns!W20=1,V43+Returns!W24*V43*(Returns!W22+$C42/10000)/4-IF(AND(Returns!W20=1,Returns!W24=0),MIN(V43,Returns!$C$6*Returns!$C$11/4),0),0)
B44: Financing line ending balance (before exit payoff) | C44: =$F42 | D44: =IF(Returns!D20=1,C44-$F42*IF(AND(Returns!D20=1,Returns!D24=0),MIN(C43,Returns!$C$6*Returns!$C$11/4),0)/Returns!$C$6,0) | E44: =IF(Returns!E20=1,D44-$F42*IF(AND(Returns!E20=1,Returns!E24=0),MIN(D43,Returns!$C$6*Returns!$C$11/4),0)/Returns!$C$6,0) | F44: =IF(Returns!F20=1,E44-$F42*IF(AND(Returns!F20=1,Returns!F24=0),MIN(E43,Returns!$C$6*Returns!$C$11/4),0)/Returns!$C$6,0) | G44: =IF(Returns!G20=1,F44-$F42*IF(AND(Returns!G20=1,Returns!G24=0),MIN(F43,Returns!$C$6*Returns!$C$11/4),0)/Returns!$C$6,0) | H44: =IF(Returns!H20=1,G44-$F42*IF(AND(Returns!H20=1,Returns!H24=0),MIN(G43,Returns!$C$6*Returns!$C$11/4),0)/Returns!$C$6,0) | I44: =IF(Returns!I20=1,H44-$F42*IF(AND(Returns!I20=1,Returns!I24=0),MIN(H43,Returns!$C$6*Returns!$C$11/4),0)/Returns!$C$6,0) | J44: =IF(Returns!J20=1,I44-$F42*IF(AND(Returns!J20=1,Returns!J24=0),MIN(I43,Returns!$C$6*Returns!$C$11/4),0)/Returns!$C$6,0) | K44: =IF(Returns!K20=1,J44-$F42*IF(AND(Returns!K20=1,Returns!K24=0),MIN(J43,Returns!$C$6*Returns!$C$11/4),0)/Returns!$C$6,0) | ... W44: =IF(Returns!W20=1,V44-$F42*IF(AND(Returns!W20=1,Returns!W24=0),MIN(V43,Returns!$C$6*Returns!$C$11/4),0)/Returns!$C$6,0)
B45: Levered net cash flow | C45: =-Returns!$C$6*(1-Returns!$D$8)+$F42 | D45: =Returns!D20*(1-Returns!D24)*C43*(Returns!D22+$C42/10000)/4+IF(AND(Returns!D20=1,Returns!D24=0),MIN(C43,Returns!$C$6*Returns!$C$11/4),0)+Returns!D21*D43*Returns!$C$12/100-Returns!D20*C44*(Returns!D22+Returns!$I$8/10000)/4-$F42*IF(AND(Returns!D20=1,Returns!D24=0),MIN(C43,Returns!$C$6*Returns!$C$11/4),0)/Returns!$C$6-Returns!D21*D44 | E45: =Returns!E20*(1-Returns!E24)*D43*(Returns!E22+$C42/10000)/4+IF(AND(Returns!E20=1,Returns!E24=0),MIN(D43,Returns!$C$6*Returns!$C$11/4),0)+Returns!E21*E43*Returns!$C$12/100-Returns!E20*D44*(Returns!E22+Returns!$I$8/10000)/4-$F42*IF(AND(Returns!E20=1,Returns!E24=0),MIN(D43,Returns!$C$6*Returns!$C$11/4),0)/Returns!$C$6-Returns!E21*E44 | F45: =Returns!F20*(1-Returns!F24)*E43*(Returns!F22+$C42/10000)/4+IF(AND(Returns!F20=1,Returns!F24=0),MIN(E43,Returns!$C$6*Returns!$C$11/4),0)+Returns!F21*F43*Returns!$C$12/100-Returns!F20*E44*(Returns!F22+Returns!$I$8/10000)/4-$F42*IF(AND(Returns!F20=1,Returns!F24=0),MIN(E43,Returns!$C$6*Returns!$C$11/4),0)/Returns!$C$6-Returns!F21*F44 | G45: =Returns!G20*(1-Returns!G24)*F43*(Returns!G22+$C42/10000)/4+IF(AND(Returns!G20=1,Returns!G24=0),MIN(F43,Returns!$C$6*Returns!$C$11/4),0)+Returns!G21*G43*Returns!$C$12/100-Returns!G20*F44*(Returns!G22+Returns!$I$8/10000)/4-$F42*IF(AND(Returns!G20=1,Returns!G24=0),MIN(F43,Returns!$C$6*Returns!$C$11/4),0)/Returns!$C$6-Returns!G21*G44 | H45: =Returns!H20*(1-Returns!H24)*G43*(Returns!H22+$C42/10000)/4+IF(AND(Returns!H20=1,Returns!H24=0),MIN(G43,Returns!$C$6*Returns!$C$11/4),0)+Returns!H21*H43*Returns!$C$12/100-Returns!H20*G44*(Returns!H22+Returns!$I$8/10000)/4-$F42*IF(AND(Returns!H20=1,Returns!H24=0),MIN(G43,Returns!$C$6*Returns!$C$11/4),0)/Returns!$C$6-Returns!H21*H44 | I45: =Returns!I20*(1-Returns!I24)*H43*(Returns!I22+$C42/10000)/4+IF(AND(Returns!I20=1,Returns!I24=0),MIN(H43,Returns!$C$6*Returns!$C$11/4),0)+Returns!I21*I43*Returns!$C$12/100-Returns!I20*H44*(Returns!I22+Returns!$I$8/10000)/4-$F42*IF(AND(Returns!I20=1,Returns!I24=0),MIN(H43,Returns!$C$6*Returns!$C$11/4),0)/Returns!$C$6-Returns!I21*I44 | J45: =Returns!J20*(1-Returns!J24)*I43*(Returns!J22+$C42/10000)/4+IF(AND(Returns!J20=1,Returns!J24=0),MIN(I43,Returns!$C$6*Returns!$C$11/4),0)+Returns!J21*J43*Returns!$C$12/100-Returns!J20*I44*(Returns!J22+Returns!$I$8/10000)/4-$F42*IF(AND(Returns!J20=1,Returns!J24=0),MIN(I43,Returns!$C$6*Returns!$C$11/4),0)/Returns!$C$6-Returns!J21*J44 | K45: =Returns!K20*(1-Returns!K24)*J43*(Returns!K22+$C42/10000)/4+IF(AND(Returns!K20=1,Returns!K24=0),MIN(J43,Returns!$C$6*Returns!$C$11/4),0)+Returns!K21*K43*Returns!$C$12/100-Returns!K20*J44*(Returns!K22+Returns!$I$8/10000)/4-$F42*IF(AND(Returns!K20=1,Returns!K24=0),MIN(J43,Returns!$C$6*Returns!$C$11/4),0)/Returns!$C$6-Returns!K21*K44 | ... W45: =Returns!W20*(1-Returns!W24)*V43*(Returns!W22+$C42/10000)/4+IF(AND(Returns!W20=1,Returns!W24=0),MIN(V43,Returns!$C$6*Returns!$C$11/4),0)+Returns!W21*W43*Returns!$C$12/100-Returns!W20*V44*(Returns!W22+Returns!$I$8/10000)/4-$F42*IF(AND(Returns!W20=1,Returns!W24=0),MIN(V43,Returns!$C$6*Returns!$C$11/4),0)/Returns!$C$6-Returns!W21*W44
B47: Spread offset +0 bps, leverage 1.25x — parameters (spread, leverage, advance rate, financing at close) | C47: =Returns!$C$7+(0) | D47: 1.25 | E47: =D47/(1+D47) | F47: =Returns!$C$6*(1-Returns!$D$8)*E47
B48: Loan ending balance (before exit payoff) | C48: =Returns!$C$6 | D48: =IF(Returns!D20=1,C48+Returns!D24*C48*(Returns!D22+$C47/10000)/4-IF(AND(Returns!D20=1,Returns!D24=0),MIN(C48,Returns!$C$6*Returns!$C$11/4),0),0) | E48: =IF(Returns!E20=1,D48+Returns!E24*D48*(Returns!E22+$C47/10000)/4-IF(AND(Returns!E20=1,Returns!E24=0),MIN(D48,Returns!$C$6*Returns!$C$11/4),0),0) | F48: =IF(Returns!F20=1,E48+Returns!F24*E48*(Returns!F22+$C47/10000)/4-IF(AND(Returns!F20=1,Returns!F24=0),MIN(E48,Returns!$C$6*Returns!$C$11/4),0),0) | G48: =IF(Returns!G20=1,F48+Returns!G24*F48*(Returns!G22+$C47/10000)/4-IF(AND(Returns!G20=1,Returns!G24=0),MIN(F48,Returns!$C$6*Returns!$C$11/4),0),0) | H48: =IF(Returns!H20=1,G48+Returns!H24*G48*(Returns!H22+$C47/10000)/4-IF(AND(Returns!H20=1,Returns!H24=0),MIN(G48,Returns!$C$6*Returns!$C$11/4),0),0) | I48: =IF(Returns!I20=1,H48+Returns!I24*H48*(Returns!I22+$C47/10000)/4-IF(AND(Returns!I20=1,Returns!I24=0),MIN(H48,Returns!$C$6*Returns!$C$11/4),0),0) | J48: =IF(Returns!J20=1,I48+Returns!J24*I48*(Returns!J22+$C47/10000)/4-IF(AND(Returns!J20=1,Returns!J24=0),MIN(I48,Returns!$C$6*Returns!$C$11/4),0),0) | K48: =IF(Returns!K20=1,J48+Returns!K24*J48*(Returns!K22+$C47/10000)/4-IF(AND(Returns!K20=1,Returns!K24=0),MIN(J48,Returns!$C$6*Returns!$C$11/4),0),0) | ... W48: =IF(Returns!W20=1,V48+Returns!W24*V48*(Returns!W22+$C47/10000)/4-IF(AND(Returns!W20=1,Returns!W24=0),MIN(V48,Returns!$C$6*Returns!$C$11/4),0),0)
B49: Financing line ending balance (before exit payoff) | C49: =$F47 | D49: =IF(Returns!D20=1,C49-$F47*IF(AND(Returns!D20=1,Returns!D24=0),MIN(C48,Returns!$C$6*Returns!$C$11/4),0)/Returns!$C$6,0) | E49: =IF(Returns!E20=1,D49-$F47*IF(AND(Returns!E20=1,Returns!E24=0),MIN(D48,Returns!$C$6*Returns!$C$11/4),0)/Returns!$C$6,0) | F49: =IF(Returns!F20=1,E49-$F47*IF(AND(Returns!F20=1,Returns!F24=0),MIN(E48,Returns!$C$6*Returns!$C$11/4),0)/Returns!$C$6,0) | G49: =IF(Returns!G20=1,F49-$F47*IF(AND(Returns!G20=1,Returns!G24=0),MIN(F48,Returns!$C$6*Returns!$C$11/4),0)/Returns!$C$6,0) | H49: =IF(Returns!H20=1,G49-$F47*IF(AND(Returns!H20=1,Returns!H24=0),MIN(G48,Returns!$C$6*Returns!$C$11/4),0)/Returns!$C$6,0) | I49: =IF(Returns!I20=1,H49-$F47*IF(AND(Returns!I20=1,Returns!I24=0),MIN(H48,Returns!$C$6*Returns!$C$11/4),0)/Returns!$C$6,0) | J49: =IF(Returns!J20=1,I49-$F47*IF(AND(Returns!J20=1,Returns!J24=0),MIN(I48,Returns!$C$6*Returns!$C$11/4),0)/Returns!$C$6,0) | K49: =IF(Returns!K20=1,J49-$F47*IF(AND(Returns!K20=1,Returns!K24=0),MIN(J48,Returns!$C$6*Returns!$C$11/4),0)/Returns!$C$6,0) | ... W49: =IF(Returns!W20=1,V49-$F47*IF(AND(Returns!W20=1,Returns!W24=0),MIN(V48,Returns!$C$6*Returns!$C$11/4),0)/Returns!$C$6,0)
B50: Levered net cash flow | C50: =-Returns!$C$6*(1-Returns!$D$8)+$F47 | D50: =Returns!D20*(1-Returns!D24)*C48*(Returns!D22+$C47/10000)/4+IF(AND(Returns!D20=1,Returns!D24=0),MIN(C48,Returns!$C$6*Returns!$C$11/4),0)+Returns!D21*D48*Returns!$C$12/100-Returns!D20*C49*(Returns!D22+Returns!$I$8/10000)/4-$F47*IF(AND(Returns!D20=1,Returns!D24=0),MIN(C48,Returns!$C$6*Returns!$C$11/4),0)/Returns!$C$6-Returns!D21*D49 | E50: =Returns!E20*(1-Returns!E24)*D48*(Returns!E22+$C47/10000)/4+IF(AND(Returns!E20=1,Returns!E24=0),MIN(D48,Returns!$C$6*Returns!$C$11/4),0)+Returns!E21*E48*Returns!$C$12/100-Returns!E20*D49*(Returns!E22+Returns!$I$8/10000)/4-$F47*IF(AND(Returns!E20=1,Returns!E24=0),MIN(D48,Returns!$C$6*Returns!$C$11/4),0)/Returns!$C$6-Returns!E21*E49 | F50: =Returns!F20*(1-Returns!F24)*E48*(Returns!F22+$C47/10000)/4+IF(AND(Returns!F20=1,Returns!F24=0),MIN(E48,Returns!$C$6*Returns!$C$11/4),0)+Returns!F21*F48*Returns!$C$12/100-Returns!F20*E49*(Returns!F22+Returns!$I$8/10000)/4-$F47*IF(AND(Returns!F20=1,Returns!F24=0),MIN(E48,Returns!$C$6*Returns!$C$11/4),0)/Returns!$C$6-Returns!F21*F49 | G50: =Returns!G20*(1-Returns!G24)*F48*(Returns!G22+$C47/10000)/4+IF(AND(Returns!G20=1,Returns!G24=0),MIN(F48,Returns!$C$6*Returns!$C$11/4),0)+Returns!G21*G48*Returns!$C$12/100-Returns!G20*F49*(Returns!G22+Returns!$I$8/10000)/4-$F47*IF(AND(Returns!G20=1,Returns!G24=0),MIN(F48,Returns!$C$6*Returns!$C$11/4),0)/Returns!$C$6-Returns!G21*G49 | H50: =Returns!H20*(1-Returns!H24)*G48*(Returns!H22+$C47/10000)/4+IF(AND(Returns!H20=1,Returns!H24=0),MIN(G48,Returns!$C$6*Returns!$C$11/4),0)+Returns!H21*H48*Returns!$C$12/100-Returns!H20*G49*(Returns!H22+Returns!$I$8/10000)/4-$F47*IF(AND(Returns!H20=1,Returns!H24=0),MIN(G48,Returns!$C$6*Returns!$C$11/4),0)/Returns!$C$6-Returns!H21*H49 | I50: =Returns!I20*(1-Returns!I24)*H48*(Returns!I22+$C47/10000)/4+IF(AND(Returns!I20=1,Returns!I24=0),MIN(H48,Returns!$C$6*Returns!$C$11/4),0)+Returns!I21*I48*Returns!$C$12/100-Returns!I20*H49*(Returns!I22+Returns!$I$8/10000)/4-$F47*IF(AND(Returns!I20=1,Returns!I24=0),MIN(H48,Returns!$C$6*Returns!$C$11/4),0)/Returns!$C$6-Returns!I21*I49 | J50: =Returns!J20*(1-Returns!J24)*I48*(Returns!J22+$C47/10000)/4+IF(AND(Returns!J20=1,Returns!J24=0),MIN(I48,Returns!$C$6*Returns!$C$11/4),0)+Returns!J21*J48*Returns!$C$12/100-Returns!J20*I49*(Returns!J22+Returns!$I$8/10000)/4-$F47*IF(AND(Returns!J20=1,Returns!J24=0),MIN(I48,Returns!$C$6*Returns!$C$11/4),0)/Returns!$C$6-Returns!J21*J49 | K50: =Returns!K20*(1-Returns!K24)*J48*(Returns!K22+$C47/10000)/4+IF(AND(Returns!K20=1,Returns!K24=0),MIN(J48,Returns!$C$6*Returns!$C$11/4),0)+Returns!K21*K48*Returns!$C$12/100-Returns!K20*J49*(Returns!K22+Returns!$I$8/10000)/4-$F47*IF(AND(Returns!K20=1,Returns!K24=0),MIN(J48,Returns!$C$6*Returns!$C$11/4),0)/Returns!$C$6-Returns!K21*K49 | ... W50: =Returns!W20*(1-Returns!W24)*V48*(Returns!W22+$C47/10000)/4+IF(AND(Returns!W20=1,Returns!W24=0),MIN(V48,Returns!$C$6*Returns!$C$11/4),0)+Returns!W21*W48*Returns!$C$12/100-Returns!W20*V49*(Returns!W22+Returns!$I$8/10000)/4-$F47*IF(AND(Returns!W20=1,Returns!W24=0),MIN(V48,Returns!$C$6*Returns!$C$11/4),0)/Returns!$C$6-Returns!W21*W49
B52: Spread offset +50 bps, leverage 0.75x — parameters (spread, leverage, advance rate, financing at close) | C52: =Returns!$C$7+(50) | D52: 0.75 | E52: =D52/(1+D52) | F52: =Returns!$C$6*(1-Returns!$D$8)*E52
B53: Loan ending balance (before exit payoff) | C53: =Returns!$C$6 | D53: =IF(Returns!D20=1,C53+Returns!D24*C53*(Returns!D22+$C52/10000)/4-IF(AND(Returns!D20=1,Returns!D24=0),MIN(C53,Returns!$C$6*Returns!$C$11/4),0),0) | E53: =IF(Returns!E20=1,D53+Returns!E24*D53*(Returns!E22+$C52/10000)/4-IF(AND(Returns!E20=1,Returns!E24=0),MIN(D53,Returns!$C$6*Returns!$C$11/4),0),0) | F53: =IF(Returns!F20=1,E53+Returns!F24*E53*(Returns!F22+$C52/10000)/4-IF(AND(Returns!F20=1,Returns!F24=0),MIN(E53,Returns!$C$6*Returns!$C$11/4),0),0) | G53: =IF(Returns!G20=1,F53+Returns!G24*F53*(Returns!G22+$C52/10000)/4-IF(AND(Returns!G20=1,Returns!G24=0),MIN(F53,Returns!$C$6*Returns!$C$11/4),0),0) | H53: =IF(Returns!H20=1,G53+Returns!H24*G53*(Returns!H22+$C52/10000)/4-IF(AND(Returns!H20=1,Returns!H24=0),MIN(G53,Returns!$C$6*Returns!$C$11/4),0),0) | I53: =IF(Returns!I20=1,H53+Returns!I24*H53*(Returns!I22+$C52/10000)/4-IF(AND(Returns!I20=1,Returns!I24=0),MIN(H53,Returns!$C$6*Returns!$C$11/4),0),0) | J53: =IF(Returns!J20=1,I53+Returns!J24*I53*(Returns!J22+$C52/10000)/4-IF(AND(Returns!J20=1,Returns!J24=0),MIN(I53,Returns!$C$6*Returns!$C$11/4),0),0) | K53: =IF(Returns!K20=1,J53+Returns!K24*J53*(Returns!K22+$C52/10000)/4-IF(AND(Returns!K20=1,Returns!K24=0),MIN(J53,Returns!$C$6*Returns!$C$11/4),0),0) | ... W53: =IF(Returns!W20=1,V53+Returns!W24*V53*(Returns!W22+$C52/10000)/4-IF(AND(Returns!W20=1,Returns!W24=0),MIN(V53,Returns!$C$6*Returns!$C$11/4),0),0)
B54: Financing line ending balance (before exit payoff) | C54: =$F52 | D54: =IF(Returns!D20=1,C54-$F52*IF(AND(Returns!D20=1,Returns!D24=0),MIN(C53,Returns!$C$6*Returns!$C$11/4),0)/Returns!$C$6,0) | E54: =IF(Returns!E20=1,D54-$F52*IF(AND(Returns!E20=1,Returns!E24=0),MIN(D53,Returns!$C$6*Returns!$C$11/4),0)/Returns!$C$6,0) | F54: =IF(Returns!F20=1,E54-$F52*IF(AND(Returns!F20=1,Returns!F24=0),MIN(E53,Returns!$C$6*Returns!$C$11/4),0)/Returns!$C$6,0) | G54: =IF(Returns!G20=1,F54-$F52*IF(AND(Returns!G20=1,Returns!G24=0),MIN(F53,Returns!$C$6*Returns!$C$11/4),0)/Returns!$C$6,0) | H54: =IF(Returns!H20=1,G54-$F52*IF(AND(Returns!H20=1,Returns!H24=0),MIN(G53,Returns!$C$6*Returns!$C$11/4),0)/Returns!$C$6,0) | I54: =IF(Returns!I20=1,H54-$F52*IF(AND(Returns!I20=1,Returns!I24=0),MIN(H53,Returns!$C$6*Returns!$C$11/4),0)/Returns!$C$6,0) | J54: =IF(Returns!J20=1,I54-$F52*IF(AND(Returns!J20=1,Returns!J24=0),MIN(I53,Returns!$C$6*Returns!$C$11/4),0)/Returns!$C$6,0) | K54: =IF(Returns!K20=1,J54-$F52*IF(AND(Returns!K20=1,Returns!K24=0),MIN(J53,Returns!$C$6*Returns!$C$11/4),0)/Returns!$C$6,0) | ... W54: =IF(Returns!W20=1,V54-$F52*IF(AND(Returns!W20=1,Returns!W24=0),MIN(V53,Returns!$C$6*Returns!$C$11/4),0)/Returns!$C$6,0)
B55: Levered net cash flow | C55: =-Returns!$C$6*(1-Returns!$D$8)+$F52 | D55: =Returns!D20*(1-Returns!D24)*C53*(Returns!D22+$C52/10000)/4+IF(AND(Returns!D20=1,Returns!D24=0),MIN(C53,Returns!$C$6*Returns!$C$11/4),0)+Returns!D21*D53*Returns!$C$12/100-Returns!D20*C54*(Returns!D22+Returns!$I$8/10000)/4-$F52*IF(AND(Returns!D20=1,Returns!D24=0),MIN(C53,Returns!$C$6*Returns!$C$11/4),0)/Returns!$C$6-Returns!D21*D54 | E55: =Returns!E20*(1-Returns!E24)*D53*(Returns!E22+$C52/10000)/4+IF(AND(Returns!E20=1,Returns!E24=0),MIN(D53,Returns!$C$6*Returns!$C$11/4),0)+Returns!E21*E53*Returns!$C$12/100-Returns!E20*D54*(Returns!E22+Returns!$I$8/10000)/4-$F52*IF(AND(Returns!E20=1,Returns!E24=0),MIN(D53,Returns!$C$6*Returns!$C$11/4),0)/Returns!$C$6-Returns!E21*E54 | F55: =Returns!F20*(1-Returns!F24)*E53*(Returns!F22+$C52/10000)/4+IF(AND(Returns!F20=1,Returns!F24=0),MIN(E53,Returns!$C$6*Returns!$C$11/4),0)+Returns!F21*F53*Returns!$C$12/100-Returns!F20*E54*(Returns!F22+Returns!$I$8/10000)/4-$F52*IF(AND(Returns!F20=1,Returns!F24=0),MIN(E53,Returns!$C$6*Returns!$C$11/4),0)/Returns!$C$6-Returns!F21*F54 | G55: =Returns!G20*(1-Returns!G24)*F53*(Returns!G22+$C52/10000)/4+IF(AND(Returns!G20=1,Returns!G24=0),MIN(F53,Returns!$C$6*Returns!$C$11/4),0)+Returns!G21*G53*Returns!$C$12/100-Returns!G20*F54*(Returns!G22+Returns!$I$8/10000)/4-$F52*IF(AND(Returns!G20=1,Returns!G24=0),MIN(F53,Returns!$C$6*Returns!$C$11/4),0)/Returns!$C$6-Returns!G21*G54 | H55: =Returns!H20*(1-Returns!H24)*G53*(Returns!H22+$C52/10000)/4+IF(AND(Returns!H20=1,Returns!H24=0),MIN(G53,Returns!$C$6*Returns!$C$11/4),0)+Returns!H21*H53*Returns!$C$12/100-Returns!H20*G54*(Returns!H22+Returns!$I$8/10000)/4-$F52*IF(AND(Returns!H20=1,Returns!H24=0),MIN(G53,Returns!$C$6*Returns!$C$11/4),0)/Returns!$C$6-Returns!H21*H54 | I55: =Returns!I20*(1-Returns!I24)*H53*(Returns!I22+$C52/10000)/4+IF(AND(Returns!I20=1,Returns!I24=0),MIN(H53,Returns!$C$6*Returns!$C$11/4),0)+Returns!I21*I53*Returns!$C$12/100-Returns!I20*H54*(Returns!I22+Returns!$I$8/10000)/4-$F52*IF(AND(Returns!I20=1,Returns!I24=0),MIN(H53,Returns!$C$6*Returns!$C$11/4),0)/Returns!$C$6-Returns!I21*I54 | J55: =Returns!J20*(1-Returns!J24)*I53*(Returns!J22+$C52/10000)/4+IF(AND(Returns!J20=1,Returns!J24=0),MIN(I53,Returns!$C$6*Returns!$C$11/4),0)+Returns!J21*J53*Returns!$C$12/100-Returns!J20*I54*(Returns!J22+Returns!$I$8/10000)/4-$F52*IF(AND(Returns!J20=1,Returns!J24=0),MIN(I53,Returns!$C$6*Returns!$C$11/4),0)/Returns!$C$6-Returns!J21*J54 | K55: =Returns!K20*(1-Returns!K24)*J53*(Returns!K22+$C52/10000)/4+IF(AND(Returns!K20=1,Returns!K24=0),MIN(J53,Returns!$C$6*Returns!$C$11/4),0)+Returns!K21*K53*Returns!$C$12/100-Returns!K20*J54*(Returns!K22+Returns!$I$8/10000)/4-$F52*IF(AND(Returns!K20=1,Returns!K24=0),MIN(J53,Returns!$C$6*Returns!$C$11/4),0)/Returns!$C$6-Returns!K21*K54 | ... W55: =Returns!W20*(1-Returns!W24)*V53*(Returns!W22+$C52/10000)/4+IF(AND(Returns!W20=1,Returns!W24=0),MIN(V53,Returns!$C$6*Returns!$C$11/4),0)+Returns!W21*W53*Returns!$C$12/100-Returns!W20*V54*(Returns!W22+Returns!$I$8/10000)/4-$F52*IF(AND(Returns!W20=1,Returns!W24=0),MIN(V53,Returns!$C$6*Returns!$C$11/4),0)/Returns!$C$6-Returns!W21*W54
B57: Spread offset +50 bps, leverage 1.00x — parameters (spread, leverage, advance rate, financing at close) | C57: =Returns!$C$7+(50) | D57: 1 | E57: =D57/(1+D57) | F57: =Returns!$C$6*(1-Returns!$D$8)*E57
B58: Loan ending balance (before exit payoff) | C58: =Returns!$C$6 | D58: =IF(Returns!D20=1,C58+Returns!D24*C58*(Returns!D22+$C57/10000)/4-IF(AND(Returns!D20=1,Returns!D24=0),MIN(C58,Returns!$C$6*Returns!$C$11/4),0),0) | E58: =IF(Returns!E20=1,D58+Returns!E24*D58*(Returns!E22+$C57/10000)/4-IF(AND(Returns!E20=1,Returns!E24=0),MIN(D58,Returns!$C$6*Returns!$C$11/4),0),0) | F58: =IF(Returns!F20=1,E58+Returns!F24*E58*(Returns!F22+$C57/10000)/4-IF(AND(Returns!F20=1,Returns!F24=0),MIN(E58,Returns!$C$6*Returns!$C$11/4),0),0) | G58: =IF(Returns!G20=1,F58+Returns!G24*F58*(Returns!G22+$C57/10000)/4-IF(AND(Returns!G20=1,Returns!G24=0),MIN(F58,Returns!$C$6*Returns!$C$11/4),0),0) | H58: =IF(Returns!H20=1,G58+Returns!H24*G58*(Returns!H22+$C57/10000)/4-IF(AND(Returns!H20=1,Returns!H24=0),MIN(G58,Returns!$C$6*Returns!$C$11/4),0),0) | I58: =IF(Returns!I20=1,H58+Returns!I24*H58*(Returns!I22+$C57/10000)/4-IF(AND(Returns!I20=1,Returns!I24=0),MIN(H58,Returns!$C$6*Returns!$C$11/4),0),0) | J58: =IF(Returns!J20=1,I58+Returns!J24*I58*(Returns!J22+$C57/10000)/4-IF(AND(Returns!J20=1,Returns!J24=0),MIN(I58,Returns!$C$6*Returns!$C$11/4),0),0) | K58: =IF(Returns!K20=1,J58+Returns!K24*J58*(Returns!K22+$C57/10000)/4-IF(AND(Returns!K20=1,Returns!K24=0),MIN(J58,Returns!$C$6*Returns!$C$11/4),0),0) | ... W58: =IF(Returns!W20=1,V58+Returns!W24*V58*(Returns!W22+$C57/10000)/4-IF(AND(Returns!W20=1,Returns!W24=0),MIN(V58,Returns!$C$6*Returns!$C$11/4),0),0)
B59: Financing line ending balance (before exit payoff) | C59: =$F57 | D59: =IF(Returns!D20=1,C59-$F57*IF(AND(Returns!D20=1,Returns!D24=0),MIN(C58,Returns!$C$6*Returns!$C$11/4),0)/Returns!$C$6,0) | E59: =IF(Returns!E20=1,D59-$F57*IF(AND(Returns!E20=1,Returns!E24=0),MIN(D58,Returns!$C$6*Returns!$C$11/4),0)/Returns!$C$6,0) | F59: =IF(Returns!F20=1,E59-$F57*IF(AND(Returns!F20=1,Returns!F24=0),MIN(E58,Returns!$C$6*Returns!$C$11/4),0)/Returns!$C$6,0) | G59: =IF(Returns!G20=1,F59-$F57*IF(AND(Returns!G20=1,Returns!G24=0),MIN(F58,Returns!$C$6*Returns!$C$11/4),0)/Returns!$C$6,0) | H59: =IF(Returns!H20=1,G59-$F57*IF(AND(Returns!H20=1,Returns!H24=0),MIN(G58,Returns!$C$6*Returns!$C$11/4),0)/Returns!$C$6,0) | I59: =IF(Returns!I20=1,H59-$F57*IF(AND(Returns!I20=1,Returns!I24=0),MIN(H58,Returns!$C$6*Returns!$C$11/4),0)/Returns!$C$6,0) | J59: =IF(Returns!J20=1,I59-$F57*IF(AND(Returns!J20=1,Returns!J24=0),MIN(I58,Returns!$C$6*Returns!$C$11/4),0)/Returns!$C$6,0) | K59: =IF(Returns!K20=1,J59-$F57*IF(AND(Returns!K20=1,Returns!K24=0),MIN(J58,Returns!$C$6*Returns!$C$11/4),0)/Returns!$C$6,0) | ... W59: =IF(Returns!W20=1,V59-$F57*IF(AND(Returns!W20=1,Returns!W24=0),MIN(V58,Returns!$C$6*Returns!$C$11/4),0)/Returns!$C$6,0)
B60: Levered net cash flow | C60: =-Returns!$C$6*(1-Returns!$D$8)+$F57 | D60: =Returns!D20*(1-Returns!D24)*C58*(Returns!D22+$C57/10000)/4+IF(AND(Returns!D20=1,Returns!D24=0),MIN(C58,Returns!$C$6*Returns!$C$11/4),0)+Returns!D21*D58*Returns!$C$12/100-Returns!D20*C59*(Returns!D22+Returns!$I$8/10000)/4-$F57*IF(AND(Returns!D20=1,Returns!D24=0),MIN(C58,Returns!$C$6*Returns!$C$11/4),0)/Returns!$C$6-Returns!D21*D59 | E60: =Returns!E20*(1-Returns!E24)*D58*(Returns!E22+$C57/10000)/4+IF(AND(Returns!E20=1,Returns!E24=0),MIN(D58,Returns!$C$6*Returns!$C$11/4),0)+Returns!E21*E58*Returns!$C$12/100-Returns!E20*D59*(Returns!E22+Returns!$I$8/10000)/4-$F57*IF(AND(Returns!E20=1,Returns!E24=0),MIN(D58,Returns!$C$6*Returns!$C$11/4),0)/Returns!$C$6-Returns!E21*E59 | F60: =Returns!F20*(1-Returns!F24)*E58*(Returns!F22+$C57/10000)/4+IF(AND(Returns!F20=1,Returns!F24=0),MIN(E58,Returns!$C$6*Returns!$C$11/4),0)+Returns!F21*F58*Returns!$C$12/100-Returns!F20*E59*(Returns!F22+Returns!$I$8/10000)/4-$F57*IF(AND(Returns!F20=1,Returns!F24=0),MIN(E58,Returns!$C$6*Returns!$C$11/4),0)/Returns!$C$6-Returns!F21*F59 | G60: =Returns!G20*(1-Returns!G24)*F58*(Returns!G22+$C57/10000)/4+IF(AND(Returns!G20=1,Returns!G24=0),MIN(F58,Returns!$C$6*Returns!$C$11/4),0)+Returns!G21*G58*Returns!$C$12/100-Returns!G20*F59*(Returns!G22+Returns!$I$8/10000)/4-$F57*IF(AND(Returns!G20=1,Returns!G24=0),MIN(F58,Returns!$C$6*Returns!$C$11/4),0)/Returns!$C$6-Returns!G21*G59 | H60: =Returns!H20*(1-Returns!H24)*G58*(Returns!H22+$C57/10000)/4+IF(AND(Returns!H20=1,Returns!H24=0),MIN(G58,Returns!$C$6*Returns!$C$11/4),0)+Returns!H21*H58*Returns!$C$12/100-Returns!H20*G59*(Returns!H22+Returns!$I$8/10000)/4-$F57*IF(AND(Returns!H20=1,Returns!H24=0),MIN(G58,Returns!$C$6*Returns!$C$11/4),0)/Returns!$C$6-Returns!H21*H59 | I60: =Returns!I20*(1-Returns!I24)*H58*(Returns!I22+$C57/10000)/4+IF(AND(Returns!I20=1,Returns!I24=0),MIN(H58,Returns!$C$6*Returns!$C$11/4),0)+Returns!I21*I58*Returns!$C$12/100-Returns!I20*H59*(Returns!I22+Returns!$I$8/10000)/4-$F57*IF(AND(Returns!I20=1,Returns!I24=0),MIN(H58,Returns!$C$6*Returns!$C$11/4),0)/Returns!$C$6-Returns!I21*I59 | J60: =Returns!J20*(1-Returns!J24)*I58*(Returns!J22+$C57/10000)/4+IF(AND(Returns!J20=1,Returns!J24=0),MIN(I58,Returns!$C$6*Returns!$C$11/4),0)+Returns!J21*J58*Returns!$C$12/100-Returns!J20*I59*(Returns!J22+Returns!$I$8/10000)/4-$F57*IF(AND(Returns!J20=1,Returns!J24=0),MIN(I58,Returns!$C$6*Returns!$C$11/4),0)/Returns!$C$6-Returns!J21*J59 | K60: =Returns!K20*(1-Returns!K24)*J58*(Returns!K22+$C57/10000)/4+IF(AND(Returns!K20=1,Returns!K24=0),MIN(J58,Returns!$C$6*Returns!$C$11/4),0)+Returns!K21*K58*Returns!$C$12/100-Returns!K20*J59*(Returns!K22+Returns!$I$8/10000)/4-$F57*IF(AND(Returns!K20=1,Returns!K24=0),MIN(J58,Returns!$C$6*Returns!$C$11/4),0)/Returns!$C$6-Returns!K21*K59 | ... W60: =Returns!W20*(1-Returns!W24)*V58*(Returns!W22+$C57/10000)/4+IF(AND(Returns!W20=1,Returns!W24=0),MIN(V58,Returns!$C$6*Returns!$C$11/4),0)+Returns!W21*W58*Returns!$C$12/100-Returns!W20*V59*(Returns!W22+Returns!$I$8/10000)/4-$F57*IF(AND(Returns!W20=1,Returns!W24=0),MIN(V58,Returns!$C$6*Returns!$C$11/4),0)/Returns!$C$6-Returns!W21*W59
B62: Spread offset +50 bps, leverage 1.25x — parameters (spread, leverage, advance rate, financing at close) | C62: =Returns!$C$7+(50) | D62: 1.25 | E62: =D62/(1+D62) | F62: =Returns!$C$6*(1-Returns!$D$8)*E62
B63: Loan ending balance (before exit payoff) | C63: =Returns!$C$6 | D63: =IF(Returns!D20=1,C63+Returns!D24*C63*(Returns!D22+$C62/10000)/4-IF(AND(Returns!D20=1,Returns!D24=0),MIN(C63,Returns!$C$6*Returns!$C$11/4),0),0) | E63: =IF(Returns!E20=1,D63+Returns!E24*D63*(Returns!E22+$C62/10000)/4-IF(AND(Returns!E20=1,Returns!E24=0),MIN(D63,Returns!$C$6*Returns!$C$11/4),0),0) | F63: =IF(Returns!F20=1,E63+Returns!F24*E63*(Returns!F22+$C62/10000)/4-IF(AND(Returns!F20=1,Returns!F24=0),MIN(E63,Returns!$C$6*Returns!$C$11/4),0),0) | G63: =IF(Returns!G20=1,F63+Returns!G24*F63*(Returns!G22+$C62/10000)/4-IF(AND(Returns!G20=1,Returns!G24=0),MIN(F63,Returns!$C$6*Returns!$C$11/4),0),0) | H63: =IF(Returns!H20=1,G63+Returns!H24*G63*(Returns!H22+$C62/10000)/4-IF(AND(Returns!H20=1,Returns!H24=0),MIN(G63,Returns!$C$6*Returns!$C$11/4),0),0) | I63: =IF(Returns!I20=1,H63+Returns!I24*H63*(Returns!I22+$C62/10000)/4-IF(AND(Returns!I20=1,Returns!I24=0),MIN(H63,Returns!$C$6*Returns!$C$11/4),0),0) | J63: =IF(Returns!J20=1,I63+Returns!J24*I63*(Returns!J22+$C62/10000)/4-IF(AND(Returns!J20=1,Returns!J24=0),MIN(I63,Returns!$C$6*Returns!$C$11/4),0),0) | K63: =IF(Returns!K20=1,J63+Returns!K24*J63*(Returns!K22+$C62/10000)/4-IF(AND(Returns!K20=1,Returns!K24=0),MIN(J63,Returns!$C$6*Returns!$C$11/4),0),0) | ... W63: =IF(Returns!W20=1,V63+Returns!W24*V63*(Returns!W22+$C62/10000)/4-IF(AND(Returns!W20=1,Returns!W24=0),MIN(V63,Returns!$C$6*Returns!$C$11/4),0),0)
B64: Financing line ending balance (before exit payoff) | C64: =$F62 | D64: =IF(Returns!D20=1,C64-$F62*IF(AND(Returns!D20=1,Returns!D24=0),MIN(C63,Returns!$C$6*Returns!$C$11/4),0)/Returns!$C$6,0) | E64: =IF(Returns!E20=1,D64-$F62*IF(AND(Returns!E20=1,Returns!E24=0),MIN(D63,Returns!$C$6*Returns!$C$11/4),0)/Returns!$C$6,0) | F64: =IF(Returns!F20=1,E64-$F62*IF(AND(Returns!F20=1,Returns!F24=0),MIN(E63,Returns!$C$6*Returns!$C$11/4),0)/Returns!$C$6,0) | G64: =IF(Returns!G20=1,F64-$F62*IF(AND(Returns!G20=1,Returns!G24=0),MIN(F63,Returns!$C$6*Returns!$C$11/4),0)/Returns!$C$6,0) | H64: =IF(Returns!H20=1,G64-$F62*IF(AND(Returns!H20=1,Returns!H24=0),MIN(G63,Returns!$C$6*Returns!$C$11/4),0)/Returns!$C$6,0) | I64: =IF(Returns!I20=1,H64-$F62*IF(AND(Returns!I20=1,Returns!I24=0),MIN(H63,Returns!$C$6*Returns!$C$11/4),0)/Returns!$C$6,0) | J64: =IF(Returns!J20=1,I64-$F62*IF(AND(Returns!J20=1,Returns!J24=0),MIN(I63,Returns!$C$6*Returns!$C$11/4),0)/Returns!$C$6,0) | K64: =IF(Returns!K20=1,J64-$F62*IF(AND(Returns!K20=1,Returns!K24=0),MIN(J63,Returns!$C$6*Returns!$C$11/4),0)/Returns!$C$6,0) | ... W64: =IF(Returns!W20=1,V64-$F62*IF(AND(Returns!W20=1,Returns!W24=0),MIN(V63,Returns!$C$6*Returns!$C$11/4),0)/Returns!$C$6,0)
B65: Levered net cash flow | C65: =-Returns!$C$6*(1-Returns!$D$8)+$F62 | D65: =Returns!D20*(1-Returns!D24)*C63*(Returns!D22+$C62/10000)/4+IF(AND(Returns!D20=1,Returns!D24=0),MIN(C63,Returns!$C$6*Returns!$C$11/4),0)+Returns!D21*D63*Returns!$C$12/100-Returns!D20*C64*(Returns!D22+Returns!$I$8/10000)/4-$F62*IF(AND(Returns!D20=1,Returns!D24=0),MIN(C63,Returns!$C$6*Returns!$C$11/4),0)/Returns!$C$6-Returns!D21*D64 | E65: =Returns!E20*(1-Returns!E24)*D63*(Returns!E22+$C62/10000)/4+IF(AND(Returns!E20=1,Returns!E24=0),MIN(D63,Returns!$C$6*Returns!$C$11/4),0)+Returns!E21*E63*Returns!$C$12/100-Returns!E20*D64*(Returns!E22+Returns!$I$8/10000)/4-$F62*IF(AND(Returns!E20=1,Returns!E24=0),MIN(D63,Returns!$C$6*Returns!$C$11/4),0)/Returns!$C$6-Returns!E21*E64 | F65: =Returns!F20*(1-Returns!F24)*E63*(Returns!F22+$C62/10000)/4+IF(AND(Returns!F20=1,Returns!F24=0),MIN(E63,Returns!$C$6*Returns!$C$11/4),0)+Returns!F21*F63*Returns!$C$12/100-Returns!F20*E64*(Returns!F22+Returns!$I$8/10000)/4-$F62*IF(AND(Returns!F20=1,Returns!F24=0),MIN(E63,Returns!$C$6*Returns!$C$11/4),0)/Returns!$C$6-Returns!F21*F64 | G65: =Returns!G20*(1-Returns!G24)*F63*(Returns!G22+$C62/10000)/4+IF(AND(Returns!G20=1,Returns!G24=0),MIN(F63,Returns!$C$6*Returns!$C$11/4),0)+Returns!G21*G63*Returns!$C$12/100-Returns!G20*F64*(Returns!G22+Returns!$I$8/10000)/4-$F62*IF(AND(Returns!G20=1,Returns!G24=0),MIN(F63,Returns!$C$6*Returns!$C$11/4),0)/Returns!$C$6-Returns!G21*G64 | H65: =Returns!H20*(1-Returns!H24)*G63*(Returns!H22+$C62/10000)/4+IF(AND(Returns!H20=1,Returns!H24=0),MIN(G63,Returns!$C$6*Returns!$C$11/4),0)+Returns!H21*H63*Returns!$C$12/100-Returns!H20*G64*(Returns!H22+Returns!$I$8/10000)/4-$F62*IF(AND(Returns!H20=1,Returns!H24=0),MIN(G63,Returns!$C$6*Returns!$C$11/4),0)/Returns!$C$6-Returns!H21*H64 | I65: =Returns!I20*(1-Returns!I24)*H63*(Returns!I22+$C62/10000)/4+IF(AND(Returns!I20=1,Returns!I24=0),MIN(H63,Returns!$C$6*Returns!$C$11/4),0)+Returns!I21*I63*Returns!$C$12/100-Returns!I20*H64*(Returns!I22+Returns!$I$8/10000)/4-$F62*IF(AND(Returns!I20=1,Returns!I24=0),MIN(H63,Returns!$C$6*Returns!$C$11/4),0)/Returns!$C$6-Returns!I21*I64 | J65: =Returns!J20*(1-Returns!J24)*I63*(Returns!J22+$C62/10000)/4+IF(AND(Returns!J20=1,Returns!J24=0),MIN(I63,Returns!$C$6*Returns!$C$11/4),0)+Returns!J21*J63*Returns!$C$12/100-Returns!J20*I64*(Returns!J22+Returns!$I$8/10000)/4-$F62*IF(AND(Returns!J20=1,Returns!J24=0),MIN(I63,Returns!$C$6*Returns!$C$11/4),0)/Returns!$C$6-Returns!J21*J64 | K65: =Returns!K20*(1-Returns!K24)*J63*(Returns!K22+$C62/10000)/4+IF(AND(Returns!K20=1,Returns!K24=0),MIN(J63,Returns!$C$6*Returns!$C$11/4),0)+Returns!K21*K63*Returns!$C$12/100-Returns!K20*J64*(Returns!K22+Returns!$I$8/10000)/4-$F62*IF(AND(Returns!K20=1,Returns!K24=0),MIN(J63,Returns!$C$6*Returns!$C$11/4),0)/Returns!$C$6-Returns!K21*K64 | ... W65: =Returns!W20*(1-Returns!W24)*V63*(Returns!W22+$C62/10000)/4+IF(AND(Returns!W20=1,Returns!W24=0),MIN(V63,Returns!$C$6*Returns!$C$11/4),0)+Returns!W21*W63*Returns!$C$12/100-Returns!W20*V64*(Returns!W22+Returns!$I$8/10000)/4-$F62*IF(AND(Returns!W20=1,Returns!W24=0),MIN(V63,Returns!$C$6*Returns!$C$11/4),0)/Returns!$C$6-Returns!W21*W64
B67: Spread offset +100 bps, leverage 0.75x — parameters (spread, leverage, advance rate, financing at close) | C67: =Returns!$C$7+(100) | D67: 0.75 | E67: =D67/(1+D67) | F67: =Returns!$C$6*(1-Returns!$D$8)*E67
B68: Loan ending balance (before exit payoff) | C68: =Returns!$C$6 | D68: =IF(Returns!D20=1,C68+Returns!D24*C68*(Returns!D22+$C67/10000)/4-IF(AND(Returns!D20=1,Returns!D24=0),MIN(C68,Returns!$C$6*Returns!$C$11/4),0),0) | E68: =IF(Returns!E20=1,D68+Returns!E24*D68*(Returns!E22+$C67/10000)/4-IF(AND(Returns!E20=1,Returns!E24=0),MIN(D68,Returns!$C$6*Returns!$C$11/4),0),0) | F68: =IF(Returns!F20=1,E68+Returns!F24*E68*(Returns!F22+$C67/10000)/4-IF(AND(Returns!F20=1,Returns!F24=0),MIN(E68,Returns!$C$6*Returns!$C$11/4),0),0) | G68: =IF(Returns!G20=1,F68+Returns!G24*F68*(Returns!G22+$C67/10000)/4-IF(AND(Returns!G20=1,Returns!G24=0),MIN(F68,Returns!$C$6*Returns!$C$11/4),0),0) | H68: =IF(Returns!H20=1,G68+Returns!H24*G68*(Returns!H22+$C67/10000)/4-IF(AND(Returns!H20=1,Returns!H24=0),MIN(G68,Returns!$C$6*Returns!$C$11/4),0),0) | I68: =IF(Returns!I20=1,H68+Returns!I24*H68*(Returns!I22+$C67/10000)/4-IF(AND(Returns!I20=1,Returns!I24=0),MIN(H68,Returns!$C$6*Returns!$C$11/4),0),0) | J68: =IF(Returns!J20=1,I68+Returns!J24*I68*(Returns!J22+$C67/10000)/4-IF(AND(Returns!J20=1,Returns!J24=0),MIN(I68,Returns!$C$6*Returns!$C$11/4),0),0) | K68: =IF(Returns!K20=1,J68+Returns!K24*J68*(Returns!K22+$C67/10000)/4-IF(AND(Returns!K20=1,Returns!K24=0),MIN(J68,Returns!$C$6*Returns!$C$11/4),0),0) | ... W68: =IF(Returns!W20=1,V68+Returns!W24*V68*(Returns!W22+$C67/10000)/4-IF(AND(Returns!W20=1,Returns!W24=0),MIN(V68,Returns!$C$6*Returns!$C$11/4),0),0)
B69: Financing line ending balance (before exit payoff) | C69: =$F67 | D69: =IF(Returns!D20=1,C69-$F67*IF(AND(Returns!D20=1,Returns!D24=0),MIN(C68,Returns!$C$6*Returns!$C$11/4),0)/Returns!$C$6,0) | E69: =IF(Returns!E20=1,D69-$F67*IF(AND(Returns!E20=1,Returns!E24=0),MIN(D68,Returns!$C$6*Returns!$C$11/4),0)/Returns!$C$6,0) | F69: =IF(Returns!F20=1,E69-$F67*IF(AND(Returns!F20=1,Returns!F24=0),MIN(E68,Returns!$C$6*Returns!$C$11/4),0)/Returns!$C$6,0) | G69: =IF(Returns!G20=1,F69-$F67*IF(AND(Returns!G20=1,Returns!G24=0),MIN(F68,Returns!$C$6*Returns!$C$11/4),0)/Returns!$C$6,0) | H69: =IF(Returns!H20=1,G69-$F67*IF(AND(Returns!H20=1,Returns!H24=0),MIN(G68,Returns!$C$6*Returns!$C$11/4),0)/Returns!$C$6,0) | I69: =IF(Returns!I20=1,H69-$F67*IF(AND(Returns!I20=1,Returns!I24=0),MIN(H68,Returns!$C$6*Returns!$C$11/4),0)/Returns!$C$6,0) | J69: =IF(Returns!J20=1,I69-$F67*IF(AND(Returns!J20=1,Returns!J24=0),MIN(I68,Returns!$C$6*Returns!$C$11/4),0)/Returns!$C$6,0) | K69: =IF(Returns!K20=1,J69-$F67*IF(AND(Returns!K20=1,Returns!K24=0),MIN(J68,Returns!$C$6*Returns!$C$11/4),0)/Returns!$C$6,0) | ... W69: =IF(Returns!W20=1,V69-$F67*IF(AND(Returns!W20=1,Returns!W24=0),MIN(V68,Returns!$C$6*Returns!$C$11/4),0)/Returns!$C$6,0)
B70: Levered net cash flow | C70: =-Returns!$C$6*(1-Returns!$D$8)+$F67 | D70: =Returns!D20*(1-Returns!D24)*C68*(Returns!D22+$C67/10000)/4+IF(AND(Returns!D20=1,Returns!D24=0),MIN(C68,Returns!$C$6*Returns!$C$11/4),0)+Returns!D21*D68*Returns!$C$12/100-Returns!D20*C69*(Returns!D22+Returns!$I$8/10000)/4-$F67*IF(AND(Returns!D20=1,Returns!D24=0),MIN(C68,Returns!$C$6*Returns!$C$11/4),0)/Returns!$C$6-Returns!D21*D69 | E70: =Returns!E20*(1-Returns!E24)*D68*(Returns!E22+$C67/10000)/4+IF(AND(Returns!E20=1,Returns!E24=0),MIN(D68,Returns!$C$6*Returns!$C$11/4),0)+Returns!E21*E68*Returns!$C$12/100-Returns!E20*D69*(Returns!E22+Returns!$I$8/10000)/4-$F67*IF(AND(Returns!E20=1,Returns!E24=0),MIN(D68,Returns!$C$6*Returns!$C$11/4),0)/Returns!$C$6-Returns!E21*E69 | F70: =Returns!F20*(1-Returns!F24)*E68*(Returns!F22+$C67/10000)/4+IF(AND(Returns!F20=1,Returns!F24=0),MIN(E68,Returns!$C$6*Returns!$C$11/4),0)+Returns!F21*F68*Returns!$C$12/100-Returns!F20*E69*(Returns!F22+Returns!$I$8/10000)/4-$F67*IF(AND(Returns!F20=1,Returns!F24=0),MIN(E68,Returns!$C$6*Returns!$C$11/4),0)/Returns!$C$6-Returns!F21*F69 | G70: =Returns!G20*(1-Returns!G24)*F68*(Returns!G22+$C67/10000)/4+IF(AND(Returns!G20=1,Returns!G24=0),MIN(F68,Returns!$C$6*Returns!$C$11/4),0)+Returns!G21*G68*Returns!$C$12/100-Returns!G20*F69*(Returns!G22+Returns!$I$8/10000)/4-$F67*IF(AND(Returns!G20=1,Returns!G24=0),MIN(F68,Returns!$C$6*Returns!$C$11/4),0)/Returns!$C$6-Returns!G21*G69 | H70: =Returns!H20*(1-Returns!H24)*G68*(Returns!H22+$C67/10000)/4+IF(AND(Returns!H20=1,Returns!H24=0),MIN(G68,Returns!$C$6*Returns!$C$11/4),0)+Returns!H21*H68*Returns!$C$12/100-Returns!H20*G69*(Returns!H22+Returns!$I$8/10000)/4-$F67*IF(AND(Returns!H20=1,Returns!H24=0),MIN(G68,Returns!$C$6*Returns!$C$11/4),0)/Returns!$C$6-Returns!H21*H69 | I70: =Returns!I20*(1-Returns!I24)*H68*(Returns!I22+$C67/10000)/4+IF(AND(Returns!I20=1,Returns!I24=0),MIN(H68,Returns!$C$6*Returns!$C$11/4),0)+Returns!I21*I68*Returns!$C$12/100-Returns!I20*H69*(Returns!I22+Returns!$I$8/10000)/4-$F67*IF(AND(Returns!I20=1,Returns!I24=0),MIN(H68,Returns!$C$6*Returns!$C$11/4),0)/Returns!$C$6-Returns!I21*I69 | J70: =Returns!J20*(1-Returns!J24)*I68*(Returns!J22+$C67/10000)/4+IF(AND(Returns!J20=1,Returns!J24=0),MIN(I68,Returns!$C$6*Returns!$C$11/4),0)+Returns!J21*J68*Returns!$C$12/100-Returns!J20*I69*(Returns!J22+Returns!$I$8/10000)/4-$F67*IF(AND(Returns!J20=1,Returns!J24=0),MIN(I68,Returns!$C$6*Returns!$C$11/4),0)/Returns!$C$6-Returns!J21*J69 | K70: =Returns!K20*(1-Returns!K24)*J68*(Returns!K22+$C67/10000)/4+IF(AND(Returns!K20=1,Returns!K24=0),MIN(J68,Returns!$C$6*Returns!$C$11/4),0)+Returns!K21*K68*Returns!$C$12/100-Returns!K20*J69*(Returns!K22+Returns!$I$8/10000)/4-$F67*IF(AND(Returns!K20=1,Returns!K24=0),MIN(J68,Returns!$C$6*Returns!$C$11/4),0)/Returns!$C$6-Returns!K21*K69 | ... W70: =Returns!W20*(1-Returns!W24)*V68*(Returns!W22+$C67/10000)/4+IF(AND(Returns!W20=1,Returns!W24=0),MIN(V68,Returns!$C$6*Returns!$C$11/4),0)+Returns!W21*W68*Returns!$C$12/100-Returns!W20*V69*(Returns!W22+Returns!$I$8/10000)/4-$F67*IF(AND(Returns!W20=1,Returns!W24=0),MIN(V68,Returns!$C$6*Returns!$C$11/4),0)/Returns!$C$6-Returns!W21*W69
B72: Spread offset +100 bps, leverage 1.00x — parameters (spread, leverage, advance rate, financing at close) | C72: =Returns!$C$7+(100) | D72: 1 | E72: =D72/(1+D72) | F72: =Returns!$C$6*(1-Returns!$D$8)*E72
B73: Loan ending balance (before exit payoff) | C73: =Returns!$C$6 | D73: =IF(Returns!D20=1,C73+Returns!D24*C73*(Returns!D22+$C72/10000)/4-IF(AND(Returns!D20=1,Returns!D24=0),MIN(C73,Returns!$C$6*Returns!$C$11/4),0),0) | E73: =IF(Returns!E20=1,D73+Returns!E24*D73*(Returns!E22+$C72/10000)/4-IF(AND(Returns!E20=1,Returns!E24=0),MIN(D73,Returns!$C$6*Returns!$C$11/4),0),0) | F73: =IF(Returns!F20=1,E73+Returns!F24*E73*(Returns!F22+$C72/10000)/4-IF(AND(Returns!F20=1,Returns!F24=0),MIN(E73,Returns!$C$6*Returns!$C$11/4),0),0) | G73: =IF(Returns!G20=1,F73+Returns!G24*F73*(Returns!G22+$C72/10000)/4-IF(AND(Returns!G20=1,Returns!G24=0),MIN(F73,Returns!$C$6*Returns!$C$11/4),0),0) | H73: =IF(Returns!H20=1,G73+Returns!H24*G73*(Returns!H22+$C72/10000)/4-IF(AND(Returns!H20=1,Returns!H24=0),MIN(G73,Returns!$C$6*Returns!$C$11/4),0),0) | I73: =IF(Returns!I20=1,H73+Returns!I24*H73*(Returns!I22+$C72/10000)/4-IF(AND(Returns!I20=1,Returns!I24=0),MIN(H73,Returns!$C$6*Returns!$C$11/4),0),0) | J73: =IF(Returns!J20=1,I73+Returns!J24*I73*(Returns!J22+$C72/10000)/4-IF(AND(Returns!J20=1,Returns!J24=0),MIN(I73,Returns!$C$6*Returns!$C$11/4),0),0) | K73: =IF(Returns!K20=1,J73+Returns!K24*J73*(Returns!K22+$C72/10000)/4-IF(AND(Returns!K20=1,Returns!K24=0),MIN(J73,Returns!$C$6*Returns!$C$11/4),0),0) | ... W73: =IF(Returns!W20=1,V73+Returns!W24*V73*(Returns!W22+$C72/10000)/4-IF(AND(Returns!W20=1,Returns!W24=0),MIN(V73,Returns!$C$6*Returns!$C$11/4),0),0)
B74: Financing line ending balance (before exit payoff) | C74: =$F72 | D74: =IF(Returns!D20=1,C74-$F72*IF(AND(Returns!D20=1,Returns!D24=0),MIN(C73,Returns!$C$6*Returns!$C$11/4),0)/Returns!$C$6,0) | E74: =IF(Returns!E20=1,D74-$F72*IF(AND(Returns!E20=1,Returns!E24=0),MIN(D73,Returns!$C$6*Returns!$C$11/4),0)/Returns!$C$6,0) | F74: =IF(Returns!F20=1,E74-$F72*IF(AND(Returns!F20=1,Returns!F24=0),MIN(E73,Returns!$C$6*Returns!$C$11/4),0)/Returns!$C$6,0) | G74: =IF(Returns!G20=1,F74-$F72*IF(AND(Returns!G20=1,Returns!G24=0),MIN(F73,Returns!$C$6*Returns!$C$11/4),0)/Returns!$C$6,0) | H74: =IF(Returns!H20=1,G74-$F72*IF(AND(Returns!H20=1,Returns!H24=0),MIN(G73,Returns!$C$6*Returns!$C$11/4),0)/Returns!$C$6,0) | I74: =IF(Returns!I20=1,H74-$F72*IF(AND(Returns!I20=1,Returns!I24=0),MIN(H73,Returns!$C$6*Returns!$C$11/4),0)/Returns!$C$6,0) | J74: =IF(Returns!J20=1,I74-$F72*IF(AND(Returns!J20=1,Returns!J24=0),MIN(I73,Returns!$C$6*Returns!$C$11/4),0)/Returns!$C$6,0) | K74: =IF(Returns!K20=1,J74-$F72*IF(AND(Returns!K20=1,Returns!K24=0),MIN(J73,Returns!$C$6*Returns!$C$11/4),0)/Returns!$C$6,0) | ... W74: =IF(Returns!W20=1,V74-$F72*IF(AND(Returns!W20=1,Returns!W24=0),MIN(V73,Returns!$C$6*Returns!$C$11/4),0)/Returns!$C$6,0)
B75: Levered net cash flow | C75: =-Returns!$C$6*(1-Returns!$D$8)+$F72 | D75: =Returns!D20*(1-Returns!D24)*C73*(Returns!D22+$C72/10000)/4+IF(AND(Returns!D20=1,Returns!D24=0),MIN(C73,Returns!$C$6*Returns!$C$11/4),0)+Returns!D21*D73*Returns!$C$12/100-Returns!D20*C74*(Returns!D22+Returns!$I$8/10000)/4-$F72*IF(AND(Returns!D20=1,Returns!D24=0),MIN(C73,Returns!$C$6*Returns!$C$11/4),0)/Returns!$C$6-Returns!D21*D74 | E75: =Returns!E20*(1-Returns!E24)*D73*(Returns!E22+$C72/10000)/4+IF(AND(Returns!E20=1,Returns!E24=0),MIN(D73,Returns!$C$6*Returns!$C$11/4),0)+Returns!E21*E73*Returns!$C$12/100-Returns!E20*D74*(Returns!E22+Returns!$I$8/10000)/4-$F72*IF(AND(Returns!E20=1,Returns!E24=0),MIN(D73,Returns!$C$6*Returns!$C$11/4),0)/Returns!$C$6-Returns!E21*E74 | F75: =Returns!F20*(1-Returns!F24)*E73*(Returns!F22+$C72/10000)/4+IF(AND(Returns!F20=1,Returns!F24=0),MIN(E73,Returns!$C$6*Returns!$C$11/4),0)+Returns!F21*F73*Returns!$C$12/100-Returns!F20*E74*(Returns!F22+Returns!$I$8/10000)/4-$F72*IF(AND(Returns!F20=1,Returns!F24=0),MIN(E73,Returns!$C$6*Returns!$C$11/4),0)/Returns!$C$6-Returns!F21*F74 | G75: =Returns!G20*(1-Returns!G24)*F73*(Returns!G22+$C72/10000)/4+IF(AND(Returns!G20=1,Returns!G24=0),MIN(F73,Returns!$C$6*Returns!$C$11/4),0)+Returns!G21*G73*Returns!$C$12/100-Returns!G20*F74*(Returns!G22+Returns!$I$8/10000)/4-$F72*IF(AND(Returns!G20=1,Returns!G24=0),MIN(F73,Returns!$C$6*Returns!$C$11/4),0)/Returns!$C$6-Returns!G21*G74 | H75: =Returns!H20*(1-Returns!H24)*G73*(Returns!H22+$C72/10000)/4+IF(AND(Returns!H20=1,Returns!H24=0),MIN(G73,Returns!$C$6*Returns!$C$11/4),0)+Returns!H21*H73*Returns!$C$12/100-Returns!H20*G74*(Returns!H22+Returns!$I$8/10000)/4-$F72*IF(AND(Returns!H20=1,Returns!H24=0),MIN(G73,Returns!$C$6*Returns!$C$11/4),0)/Returns!$C$6-Returns!H21*H74 | I75: =Returns!I20*(1-Returns!I24)*H73*(Returns!I22+$C72/10000)/4+IF(AND(Returns!I20=1,Returns!I24=0),MIN(H73,Returns!$C$6*Returns!$C$11/4),0)+Returns!I21*I73*Returns!$C$12/100-Returns!I20*H74*(Returns!I22+Returns!$I$8/10000)/4-$F72*IF(AND(Returns!I20=1,Returns!I24=0),MIN(H73,Returns!$C$6*Returns!$C$11/4),0)/Returns!$C$6-Returns!I21*I74 | J75: =Returns!J20*(1-Returns!J24)*I73*(Returns!J22+$C72/10000)/4+IF(AND(Returns!J20=1,Returns!J24=0),MIN(I73,Returns!$C$6*Returns!$C$11/4),0)+Returns!J21*J73*Returns!$C$12/100-Returns!J20*I74*(Returns!J22+Returns!$I$8/10000)/4-$F72*IF(AND(Returns!J20=1,Returns!J24=0),MIN(I73,Returns!$C$6*Returns!$C$11/4),0)/Returns!$C$6-Returns!J21*J74 | K75: =Returns!K20*(1-Returns!K24)*J73*(Returns!K22+$C72/10000)/4+IF(AND(Returns!K20=1,Returns!K24=0),MIN(J73,Returns!$C$6*Returns!$C$11/4),0)+Returns!K21*K73*Returns!$C$12/100-Returns!K20*J74*(Returns!K22+Returns!$I$8/10000)/4-$F72*IF(AND(Returns!K20=1,Returns!K24=0),MIN(J73,Returns!$C$6*Returns!$C$11/4),0)/Returns!$C$6-Returns!K21*K74 | ... W75: =Returns!W20*(1-Returns!W24)*V73*(Returns!W22+$C72/10000)/4+IF(AND(Returns!W20=1,Returns!W24=0),MIN(V73,Returns!$C$6*Returns!$C$11/4),0)+Returns!W21*W73*Returns!$C$12/100-Returns!W20*V74*(Returns!W22+Returns!$I$8/10000)/4-$F72*IF(AND(Returns!W20=1,Returns!W24=0),MIN(V73,Returns!$C$6*Returns!$C$11/4),0)/Returns!$C$6-Returns!W21*W74
B77: Spread offset +100 bps, leverage 1.25x — parameters (spread, leverage, advance rate, financing at close) | C77: =Returns!$C$7+(100) | D77: 1.25 | E77: =D77/(1+D77) | F77: =Returns!$C$6*(1-Returns!$D$8)*E77
B78: Loan ending balance (before exit payoff) | C78: =Returns!$C$6 | D78: =IF(Returns!D20=1,C78+Returns!D24*C78*(Returns!D22+$C77/10000)/4-IF(AND(Returns!D20=1,Returns!D24=0),MIN(C78,Returns!$C$6*Returns!$C$11/4),0),0) | E78: =IF(Returns!E20=1,D78+Returns!E24*D78*(Returns!E22+$C77/10000)/4-IF(AND(Returns!E20=1,Returns!E24=0),MIN(D78,Returns!$C$6*Returns!$C$11/4),0),0) | F78: =IF(Returns!F20=1,E78+Returns!F24*E78*(Returns!F22+$C77/10000)/4-IF(AND(Returns!F20=1,Returns!F24=0),MIN(E78,Returns!$C$6*Returns!$C$11/4),0),0) | G78: =IF(Returns!G20=1,F78+Returns!G24*F78*(Returns!G22+$C77/10000)/4-IF(AND(Returns!G20=1,Returns!G24=0),MIN(F78,Returns!$C$6*Returns!$C$11/4),0),0) | H78: =IF(Returns!H20=1,G78+Returns!H24*G78*(Returns!H22+$C77/10000)/4-IF(AND(Returns!H20=1,Returns!H24=0),MIN(G78,Returns!$C$6*Returns!$C$11/4),0),0) | I78: =IF(Returns!I20=1,H78+Returns!I24*H78*(Returns!I22+$C77/10000)/4-IF(AND(Returns!I20=1,Returns!I24=0),MIN(H78,Returns!$C$6*Returns!$C$11/4),0),0) | J78: =IF(Returns!J20=1,I78+Returns!J24*I78*(Returns!J22+$C77/10000)/4-IF(AND(Returns!J20=1,Returns!J24=0),MIN(I78,Returns!$C$6*Returns!$C$11/4),0),0) | K78: =IF(Returns!K20=1,J78+Returns!K24*J78*(Returns!K22+$C77/10000)/4-IF(AND(Returns!K20=1,Returns!K24=0),MIN(J78,Returns!$C$6*Returns!$C$11/4),0),0) | ... W78: =IF(Returns!W20=1,V78+Returns!W24*V78*(Returns!W22+$C77/10000)/4-IF(AND(Returns!W20=1,Returns!W24=0),MIN(V78,Returns!$C$6*Returns!$C$11/4),0),0)
B79: Financing line ending balance (before exit payoff) | C79: =$F77 | D79: =IF(Returns!D20=1,C79-$F77*IF(AND(Returns!D20=1,Returns!D24=0),MIN(C78,Returns!$C$6*Returns!$C$11/4),0)/Returns!$C$6,0) | E79: =IF(Returns!E20=1,D79-$F77*IF(AND(Returns!E20=1,Returns!E24=0),MIN(D78,Returns!$C$6*Returns!$C$11/4),0)/Returns!$C$6,0) | F79: =IF(Returns!F20=1,E79-$F77*IF(AND(Returns!F20=1,Returns!F24=0),MIN(E78,Returns!$C$6*Returns!$C$11/4),0)/Returns!$C$6,0) | G79: =IF(Returns!G20=1,F79-$F77*IF(AND(Returns!G20=1,Returns!G24=0),MIN(F78,Returns!$C$6*Returns!$C$11/4),0)/Returns!$C$6,0) | H79: =IF(Returns!H20=1,G79-$F77*IF(AND(Returns!H20=1,Returns!H24=0),MIN(G78,Returns!$C$6*Returns!$C$11/4),0)/Returns!$C$6,0) | I79: =IF(Returns!I20=1,H79-$F77*IF(AND(Returns!I20=1,Returns!I24=0),MIN(H78,Returns!$C$6*Returns!$C$11/4),0)/Returns!$C$6,0) | J79: =IF(Returns!J20=1,I79-$F77*IF(AND(Returns!J20=1,Returns!J24=0),MIN(I78,Returns!$C$6*Returns!$C$11/4),0)/Returns!$C$6,0) | K79: =IF(Returns!K20=1,J79-$F77*IF(AND(Returns!K20=1,Returns!K24=0),MIN(J78,Returns!$C$6*Returns!$C$11/4),0)/Returns!$C$6,0) | ... W79: =IF(Returns!W20=1,V79-$F77*IF(AND(Returns!W20=1,Returns!W24=0),MIN(V78,Returns!$C$6*Returns!$C$11/4),0)/Returns!$C$6,0)
B80: Levered net cash flow | C80: =-Returns!$C$6*(1-Returns!$D$8)+$F77 | D80: =Returns!D20*(1-Returns!D24)*C78*(Returns!D22+$C77/10000)/4+IF(AND(Returns!D20=1,Returns!D24=0),MIN(C78,Returns!$C$6*Returns!$C$11/4),0)+Returns!D21*D78*Returns!$C$12/100-Returns!D20*C79*(Returns!D22+Returns!$I$8/10000)/4-$F77*IF(AND(Returns!D20=1,Returns!D24=0),MIN(C78,Returns!$C$6*Returns!$C$11/4),0)/Returns!$C$6-Returns!D21*D79 | E80: =Returns!E20*(1-Returns!E24)*D78*(Returns!E22+$C77/10000)/4+IF(AND(Returns!E20=1,Returns!E24=0),MIN(D78,Returns!$C$6*Returns!$C$11/4),0)+Returns!E21*E78*Returns!$C$12/100-Returns!E20*D79*(Returns!E22+Returns!$I$8/10000)/4-$F77*IF(AND(Returns!E20=1,Returns!E24=0),MIN(D78,Returns!$C$6*Returns!$C$11/4),0)/Returns!$C$6-Returns!E21*E79 | F80: =Returns!F20*(1-Returns!F24)*E78*(Returns!F22+$C77/10000)/4+IF(AND(Returns!F20=1,Returns!F24=0),MIN(E78,Returns!$C$6*Returns!$C$11/4),0)+Returns!F21*F78*Returns!$C$12/100-Returns!F20*E79*(Returns!F22+Returns!$I$8/10000)/4-$F77*IF(AND(Returns!F20=1,Returns!F24=0),MIN(E78,Returns!$C$6*Returns!$C$11/4),0)/Returns!$C$6-Returns!F21*F79 | G80: =Returns!G20*(1-Returns!G24)*F78*(Returns!G22+$C77/10000)/4+IF(AND(Returns!G20=1,Returns!G24=0),MIN(F78,Returns!$C$6*Returns!$C$11/4),0)+Returns!G21*G78*Returns!$C$12/100-Returns!G20*F79*(Returns!G22+Returns!$I$8/10000)/4-$F77*IF(AND(Returns!G20=1,Returns!G24=0),MIN(F78,Returns!$C$6*Returns!$C$11/4),0)/Returns!$C$6-Returns!G21*G79 | H80: =Returns!H20*(1-Returns!H24)*G78*(Returns!H22+$C77/10000)/4+IF(AND(Returns!H20=1,Returns!H24=0),MIN(G78,Returns!$C$6*Returns!$C$11/4),0)+Returns!H21*H78*Returns!$C$12/100-Returns!H20*G79*(Returns!H22+Returns!$I$8/10000)/4-$F77*IF(AND(Returns!H20=1,Returns!H24=0),MIN(G78,Returns!$C$6*Returns!$C$11/4),0)/Returns!$C$6-Returns!H21*H79 | I80: =Returns!I20*(1-Returns!I24)*H78*(Returns!I22+$C77/10000)/4+IF(AND(Returns!I20=1,Returns!I24=0),MIN(H78,Returns!$C$6*Returns!$C$11/4),0)+Returns!I21*I78*Returns!$C$12/100-Returns!I20*H79*(Returns!I22+Returns!$I$8/10000)/4-$F77*IF(AND(Returns!I20=1,Returns!I24=0),MIN(H78,Returns!$C$6*Returns!$C$11/4),0)/Returns!$C$6-Returns!I21*I79 | J80: =Returns!J20*(1-Returns!J24)*I78*(Returns!J22+$C77/10000)/4+IF(AND(Returns!J20=1,Returns!J24=0),MIN(I78,Returns!$C$6*Returns!$C$11/4),0)+Returns!J21*J78*Returns!$C$12/100-Returns!J20*I79*(Returns!J22+Returns!$I$8/10000)/4-$F77*IF(AND(Returns!J20=1,Returns!J24=0),MIN(I78,Returns!$C$6*Returns!$C$11/4),0)/Returns!$C$6-Returns!J21*J79 | K80: =Returns!K20*(1-Returns!K24)*J78*(Returns!K22+$C77/10000)/4+IF(AND(Returns!K20=1,Returns!K24=0),MIN(J78,Returns!$C$6*Returns!$C$11/4),0)+Returns!K21*K78*Returns!$C$12/100-Returns!K20*J79*(Returns!K22+Returns!$I$8/10000)/4-$F77*IF(AND(Returns!K20=1,Returns!K24=0),MIN(J78,Returns!$C$6*Returns!$C$11/4),0)/Returns!$C$6-Returns!K21*K79 | ... W80: =Returns!W20*(1-Returns!W24)*V78*(Returns!W22+$C77/10000)/4+IF(AND(Returns!W20=1,Returns!W24=0),MIN(V78,Returns!$C$6*Returns!$C$11/4),0)+Returns!W21*W78*Returns!$C$12/100-Returns!W20*V79*(Returns!W22+Returns!$I$8/10000)/4-$F77*IF(AND(Returns!W20=1,Returns!W24=0),MIN(V78,Returns!$C$6*Returns!$C$11/4),0)/Returns!$C$6-Returns!W21*W79
